{
  "_id": "674e524064788cc741419c1e",
  "achievementsThatReward": [],
  "appearanceId": 0,
  "castInDiagonal": false,
  "castInLine": false,
  "castTestLos": false,
  "className": "ItemData",
  "craftConditionalCriterion": "",
  "craftFeasibleCriterion": "SC!5|ST!5",
  "craftVisibleCriterion": "SC!5|ST!5",
  "craftXpRatio": -1,
  "createdAt": "2024-12-03T00:35:12.820Z",
  "criterions": "",
  "criterionsTarget": "",
  "description": {
    "de": "Diese Handschuhe schützen eure Hände vortrefflich, wenn ihr mal wieder Backpfeifen verteilen müsst. Man kann sie anschließend auswringen, um das nötige Schmierfett zur Zubereitung von Schweinedrachen-Schmalz zu gewinnen.",
    "en": "Excellent for protecting your hands during a boxing match, this glove can be spun to collect the necessary fat to make potted dragon pig.",
    "es": "Excelente para proteger tus manos durante una sesión de distribución de guantazos. Luego puedes escurrirlos para obtener la grasa necesaria para cocinar paté de Dragocerdo.",
    "fr": "Excellent pour protéger vos mains lors d'une séance de distribution de baffes, ce gantelet peut ensuite être essoré pour récupérer la graisse nécessaire à la confection de rillettes de Dragon Cochon.",
    "id": "101674",
    "pt": "Excelente para proteger suas mãos durante uma partida de boxe, essa luva pode ser usada para coletar a gordura de dragão-porco em conserva."
  },
  "dropMonsterIds": [],
  "dropSubAreaIds": [],
  "dropTemporisMonsterIds": [],
  "effects": [
    {
      "category": 0,
      "characteristic": 11,
      "effectId": 125,
      "elementId": -1,
      "from": 41,
      "to": 60
    },
    {
      "category": 0,
      "characteristic": 12,
      "effectId": 124,
      "elementId": -1,
      "from": 11,
      "to": 15
    },
    {
      "category": 0,
      "characteristic": 25,
      "effectId": 138,
      "elementId": 5,
      "from": 21,
      "to": 25
    },
    {
      "category": 0,
      "characteristic": 26,
      "effectId": 182,
      "elementId": -1,
      "from": 1,
      "to": 0
    },
    {
      "category": 0,
      "characteristic": 92,
      "effectId": 430,
      "elementId": 0,
      "from": 2,
      "to": 3
    },
    {
      "category": 0,
      "characteristic": 88,
      "effectId": 422,
      "elementId": 1,
      "from": 2,
      "to": 3
    },
    {
      "category": 0,
      "characteristic": 89,
      "effectId": 424,
      "elementId": 2,
      "from": 2,
      "to": 3
    },
    {
      "category": 0,
      "characteristic": 79,
      "effectId": 753,
      "elementId": -1,
      "from": 2,
      "to": 3
    },
    {
      "category": 0,
      "characteristic": 83,
      "effectId": 412,
      "elementId": -1,
      "from": 2,
      "to": 3
    },
    {
      "category": 0,
      "characteristic": 84,
      "effectId": 414,
      "elementId": 5,
      "from": 2,
      "to": 3
    }
  ],
  "enhanceable": true,
  "etheral": false,
  "evolutiveEffectIds": [],
  "exchangeable": true,
  "favoriteRecyclingSubareas": [],
  "favoriteSubAreas": [],
  "favoriteSubAreasBonus": 0,
  "hasLivingObjectSkinJntMood": false,
  "hasRecipe": true,
  "hideEffects": false,
  "iconId": 9236,
  "id": 12372,
  "img": "https://api.dofusdb.fr/img/items/9236.png",
  "importantNotice": {
    "id": "0"
  },
  "isColorable": false,
  "isLegendary": false,
  "isSaleable": true,
  "itemSet": {
    "_id": "674e523f64788cc741418170",
    "bonusIsSecret": false,
    "className": "ItemSetData",
    "createdAt": "2024-12-03T00:35:11.399Z",
    "effects": [
      [],
      [
        {
          "category": 0,
          "characteristic": 15,
          "effectId": 126,
          "elementId": 2,
          "from": 20,
          "to": 0
        },
        {
          "category": 0,
          "characteristic": 10,
          "effectId": 118,
          "elementId": 1,
          "from": 20,
          "to": 0
        },
        {
          "category": 0,
          "characteristic": 84,
          "effectId": 414,
          "elementId": 5,
          "from": 10,
          "to": 0
        },
        {
          "category": 0,
          "characteristic": 11,
          "effectId": 125,
          "elementId": -1,
          "from": 120,
          "to": 0
        }
      ],
      [
        {
          "category": 0,
          "characteristic": 15,
          "effectId": 126,
          "elementId": 2,
          "from": 20,
          "to": 0
        },
        {
          "category": 0,
          "characteristic": 10,
          "effectId": 118,
          "elementId": 1,
          "from": 20,
          "to": 0
        },
        {
          "category": 0,
          "characteristic": 84,
          "effectId": 414,
          "elementId": 5,
          "from": 10,
          "to": 0
        },
        {
          "category": 0,
          "characteristic": 11,
          "effectId": 125,
          "elementId": -1,
          "from": 120,
          "to": 0
        },
        {
          "category": 0,
          "characteristic": 1,
          "effectId": 111,
          "elementId": -1,
          "from": 1,
          "to": 0
        }
      ],
      [
        {
          "category": 0,
          "characteristic": 15,
          "effectId": 126,
          "elementId": 2,
          "from": 20,
          "to": 0
        },
        {
          "category": 0,
          "characteristic": 10,
          "effectId": 118,
          "elementId": 1,
          "from": 20,
          "to": 0
        },
        {
          "category": 0,
          "characteristic": 84,
          "effectId": 414,
          "elementId": 5,
          "from": 20,
          "to": 0
        },
        {
          "category": 0,
          "characteristic": 11,
          "effectId": 125,
          "elementId": -1,
          "from": 120,
          "to": 0
        },
        {
          "category": 0,
          "characteristic": 1,
          "effectId": 111,
          "elementId": -1,
          "from": 1,
          "to": 0
        },
        {
          "category": 0,
          "characteristic": 19,
          "effectId": 117,
          "elementId": -1,
          "from": 1,
          "to": 0
        }
      ]
    ],
    "id": 215,
    "isCosmetic": false,
    "items": [
      12370,
      12371,
      12372,
      12373
    ],
    "level": 103,
    "m_id": 215,
    "name": {
      "de": "Gorgoyl-Set",
      "en": "Gorgoyle Set",
      "es": "Set de marranárgola",
      "fr": "Panoplie du Gorgouille",
      "id": "60059",
      "pt": "Conjunto do Górgula"
    },
    "possibleEffects": [
      [],
      [
        {
          "baseEffectId": 7,
          "className": "EffectInstanceDice",
          "delay": 0,
          "diceNum": 20,
          "diceSide": 0,
          "dispellable": 1,
          "displayZero": false,
          "duration": 0,
          "effectElement": -1,
          "effectId": 126,
          "effectTriggerDuration": 0,
          "effectUid": 0,
          "forClientOnly": false,
          "group": 0,
          "m_flags": 8,
          "modificator": 0,
          "order": 0,
          "random": 0,
          "spellId": -1,
          "targetId": 0,
          "targetMask": "",
          "trigger": false,
          "triggers": "",
          "value": 0,
          "visibleInBuffUi": false,
          "visibleInFightLog": false,
          "visibleInTooltip": false,
          "visibleOnTerrain": true,
          "zoneDescr": {
            "cellIds": [],
            "damageDecreaseStepPercent": 10,
            "isStopAtTarget": false,
            "maxDamageDecreaseApplyCount": 4,
            "param1": 1,
            "param2": 0,
            "shape": 67
          }
        },
        {
          "baseEffectId": 4,
          "className": "EffectInstanceDice",
          "delay": 0,
          "diceNum": 20,
          "diceSide": 0,
          "dispellable": 1,
          "displayZero": false,
          "duration": 0,
          "effectElement": -1,
          "effectId": 118,
          "effectTriggerDuration": 0,
          "effectUid": 0,
          "forClientOnly": false,
          "group": 0,
          "m_flags": 8,
          "modificator": 0,
          "order": 0,
          "random": 0,
          "spellId": -1,
          "targetId": 0,
          "targetMask": "",
          "trigger": false,
          "triggers": "",
          "value": 0,
          "visibleInBuffUi": false,
          "visibleInFightLog": false,
          "visibleInTooltip": false,
          "visibleOnTerrain": true,
          "zoneDescr": {
            "cellIds": [],
            "damageDecreaseStepPercent": 10,
            "isStopAtTarget": false,
            "maxDamageDecreaseApplyCount": 4,
            "param1": 1,
            "param2": 0,
            "shape": 67
          }
        },
        {
          "baseEffectId": 357,
          "className": "EffectInstanceDice",
          "delay": 0,
          "diceNum": 10,
          "diceSide": 0,
          "dispellable": 1,
          "displayZero": false,
          "duration": 0,
          "effectElement": -1,
          "effectId": 414,
          "effectTriggerDuration": 0,
          "effectUid": 0,
          "forClientOnly": false,
          "group": 0,
          "m_flags": 8,
          "modificator": 0,
          "order": 0,
          "random": 0,
          "spellId": -1,
          "targetId": 0,
          "targetMask": "",
          "trigger": false,
          "triggers": "",
          "value": 0,
          "visibleInBuffUi": false,
          "visibleInFightLog": false,
          "visibleInTooltip": false,
          "visibleOnTerrain": true,
          "zoneDescr": {
            "cellIds": [],
            "damageDecreaseStepPercent": 10,
            "isStopAtTarget": false,
            "maxDamageDecreaseApplyCount": 4,
            "param1": 1,
            "param2": 0,
            "shape": 67
          }
        },
        {
          "baseEffectId": 5,
          "className": "EffectInstanceDice",
          "delay": 0,
          "diceNum": 120,
          "diceSide": 0,
          "dispellable": 1,
          "displayZero": false,
          "duration": 0,
          "effectElement": -1,
          "effectId": 125,
          "effectTriggerDuration": 0,
          "effectUid": 0,
          "forClientOnly": false,
          "group": 0,
          "m_flags": 8,
          "modificator": 0,
          "order": 0,
          "random": 0,
          "spellId": -1,
          "targetId": 0,
          "targetMask": "",
          "trigger": false,
          "triggers": "",
          "value": 0,
          "visibleInBuffUi": false,
          "visibleInFightLog": false,
          "visibleInTooltip": false,
          "visibleOnTerrain": true,
          "zoneDescr": {
            "cellIds": [],
            "damageDecreaseStepPercent": 10,
            "isStopAtTarget": false,
            "maxDamageDecreaseApplyCount": 4,
            "param1": 1,
            "param2": 0,
            "shape": 67
          }
        }
      ],
      [
        {
          "baseEffectId": 7,
          "className": "EffectInstanceDice",
          "delay": 0,
          "diceNum": 20,
          "diceSide": 0,
          "dispellable": 1,
          "displayZero": false,
          "duration": 0,
          "effectElement": -1,
          "effectId": 126,
          "effectTriggerDuration": 0,
          "effectUid": 0,
          "forClientOnly": false,
          "group": 0,
          "m_flags": 8,
          "modificator": 0,
          "order": 0,
          "random": 0,
          "spellId": -1,
          "targetId": 0,
          "targetMask": "",
          "trigger": false,
          "triggers": "",
          "value": 0,
          "visibleInBuffUi": false,
          "visibleInFightLog": false,
          "visibleInTooltip": false,
          "visibleOnTerrain": true,
          "zoneDescr": {
            "cellIds": [],
            "damageDecreaseStepPercent": 10,
            "isStopAtTarget": false,
            "maxDamageDecreaseApplyCount": 4,
            "param1": 1,
            "param2": 0,
            "shape": 67
          }
        },
        {
          "baseEffectId": 4,
          "className": "EffectInstanceDice",
          "delay": 0,
          "diceNum": 20,
          "diceSide": 0,
          "dispellable": 1,
          "displayZero": false,
          "duration": 0,
          "effectElement": -1,
          "effectId": 118,
          "effectTriggerDuration": 0,
          "effectUid": 0,
          "forClientOnly": false,
          "group": 0,
          "m_flags": 8,
          "modificator": 0,
          "order": 0,
          "random": 0,
          "spellId": -1,
          "targetId": 0,
          "targetMask": "",
          "trigger": false,
          "triggers": "",
          "value": 0,
          "visibleInBuffUi": false,
          "visibleInFightLog": false,
          "visibleInTooltip": false,
          "visibleOnTerrain": true,
          "zoneDescr": {
            "cellIds": [],
            "damageDecreaseStepPercent": 10,
            "isStopAtTarget": false,
            "maxDamageDecreaseApplyCount": 4,
            "param1": 1,
            "param2": 0,
            "shape": 67
          }
        },
        {
          "baseEffectId": 357,
          "className": "EffectInstanceDice",
          "delay": 0,
          "diceNum": 10,
          "diceSide": 0,
          "dispellable": 1,
          "displayZero": false,
          "duration": 0,
          "effectElement": -1,
          "effectId": 414,
          "effectTriggerDuration": 0,
          "effectUid": 0,
          "forClientOnly": false,
          "group": 0,
          "m_flags": 8,
          "modificator": 0,
          "order": 0,
          "random": 0,
          "spellId": -1,
          "targetId": 0,
          "targetMask": "",
          "trigger": false,
          "triggers": "",
          "value": 0,
          "visibleInBuffUi": false,
          "visibleInFightLog": false,
          "visibleInTooltip": false,
          "visibleOnTerrain": true,
          "zoneDescr": {
            "cellIds": [],
            "damageDecreaseStepPercent": 10,
            "isStopAtTarget": false,
            "maxDamageDecreaseApplyCount": 4,
            "param1": 1,
            "param2": 0,
            "shape": 67
          }
        },
        {
          "baseEffectId": 5,
          "className": "EffectInstanceDice",
          "delay": 0,
          "diceNum": 120,
          "diceSide": 0,
          "dispellable": 1,
          "displayZero": false,
          "duration": 0,
          "effectElement": -1,
          "effectId": 125,
          "effectTriggerDuration": 0,
          "effectUid": 0,
          "forClientOnly": false,
          "group": 0,
          "m_flags": 8,
          "modificator": 0,
          "order": 0,
          "random": 0,
          "spellId": -1,
          "targetId": 0,
          "targetMask": "",
          "trigger": false,
          "triggers": "",
          "value": 0,
          "visibleInBuffUi": false,
          "visibleInFightLog": false,
          "visibleInTooltip": false,
          "visibleOnTerrain": true,
          "zoneDescr": {
            "cellIds": [],
            "damageDecreaseStepPercent": 10,
            "isStopAtTarget": false,
            "maxDamageDecreaseApplyCount": 4,
            "param1": 1,
            "param2": 0,
            "shape": 67
          }
        },
        {
          "baseEffectId": 2,
          "className": "EffectInstanceDice",
          "delay": 0,
          "diceNum": 1,
          "diceSide": 0,
          "dispellable": 1,
          "displayZero": false,
          "duration": 0,
          "effectElement": -1,
          "effectId": 111,
          "effectTriggerDuration": 0,
          "effectUid": 0,
          "forClientOnly": false,
          "group": 0,
          "m_flags": 8,
          "modificator": 0,
          "order": 0,
          "random": 0,
          "spellId": -1,
          "targetId": 0,
          "targetMask": "",
          "trigger": false,
          "triggers": "",
          "value": 0,
          "visibleInBuffUi": false,
          "visibleInFightLog": false,
          "visibleInTooltip": false,
          "visibleOnTerrain": true,
          "zoneDescr": {
            "cellIds": [],
            "damageDecreaseStepPercent": 10,
            "isStopAtTarget": false,
            "maxDamageDecreaseApplyCount": 4,
            "param1": 1,
            "param2": 0,
            "shape": 67
          }
        }
      ],
      [
        {
          "baseEffectId": 7,
          "className": "EffectInstanceDice",
          "delay": 0,
          "diceNum": 20,
          "diceSide": 0,
          "dispellable": 1,
          "displayZero": false,
          "duration": 0,
          "effectElement": -1,
          "effectId": 126,
          "effectTriggerDuration": 0,
          "effectUid": 0,
          "forClientOnly": false,
          "group": 0,
          "m_flags": 8,
          "modificator": 0,
          "order": 0,
          "random": 0,
          "spellId": -1,
          "targetId": 0,
          "targetMask": "",
          "trigger": false,
          "triggers": "",
          "value": 0,
          "visibleInBuffUi": false,
          "visibleInFightLog": false,
          "visibleInTooltip": false,
          "visibleOnTerrain": true,
          "zoneDescr": {
            "cellIds": [],
            "damageDecreaseStepPercent": 10,
            "isStopAtTarget": false,
            "maxDamageDecreaseApplyCount": 4,
            "param1": 1,
            "param2": 0,
            "shape": 67
          }
        },
        {
          "baseEffectId": 4,
          "className": "EffectInstanceDice",
          "delay": 0,
          "diceNum": 20,
          "diceSide": 0,
          "dispellable": 1,
          "displayZero": false,
          "duration": 0,
          "effectElement": -1,
          "effectId": 118,
          "effectTriggerDuration": 0,
          "effectUid": 0,
          "forClientOnly": false,
          "group": 0,
          "m_flags": 8,
          "modificator": 0,
          "order": 0,
          "random": 0,
          "spellId": -1,
          "targetId": 0,
          "targetMask": "",
          "trigger": false,
          "triggers": "",
          "value": 0,
          "visibleInBuffUi": false,
          "visibleInFightLog": false,
          "visibleInTooltip": false,
          "visibleOnTerrain": true,
          "zoneDescr": {
            "cellIds": [],
            "damageDecreaseStepPercent": 10,
            "isStopAtTarget": false,
            "maxDamageDecreaseApplyCount": 4,
            "param1": 1,
            "param2": 0,
            "shape": 67
          }
        },
        {
          "baseEffectId": 357,
          "className": "EffectInstanceDice",
          "delay": 0,
          "diceNum": 20,
          "diceSide": 0,
          "dispellable": 1,
          "displayZero": false,
          "duration": 0,
          "effectElement": -1,
          "effectId": 414,
          "effectTriggerDuration": 0,
          "effectUid": 0,
          "forClientOnly": false,
          "group": 0,
          "m_flags": 8,
          "modificator": 0,
          "order": 0,
          "random": 0,
          "spellId": -1,
          "targetId": 0,
          "targetMask": "",
          "trigger": false,
          "triggers": "",
          "value": 0,
          "visibleInBuffUi": false,
          "visibleInFightLog": false,
          "visibleInTooltip": false,
          "visibleOnTerrain": true,
          "zoneDescr": {
            "cellIds": [],
            "damageDecreaseStepPercent": 10,
            "isStopAtTarget": false,
            "maxDamageDecreaseApplyCount": 4,
            "param1": 1,
            "param2": 0,
            "shape": 67
          }
        },
        {
          "baseEffectId": 5,
          "className": "EffectInstanceDice",
          "delay": 0,
          "diceNum": 120,
          "diceSide": 0,
          "dispellable": 1,
          "displayZero": false,
          "duration": 0,
          "effectElement": -1,
          "effectId": 125,
          "effectTriggerDuration": 0,
          "effectUid": 0,
          "forClientOnly": false,
          "group": 0,
          "m_flags": 8,
          "modificator": 0,
          "order": 0,
          "random": 0,
          "spellId": -1,
          "targetId": 0,
          "targetMask": "",
          "trigger": false,
          "triggers": "",
          "value": 0,
          "visibleInBuffUi": false,
          "visibleInFightLog": false,
          "visibleInTooltip": false,
          "visibleOnTerrain": true,
          "zoneDescr": {
            "cellIds": [],
            "damageDecreaseStepPercent": 10,
            "isStopAtTarget": false,
            "maxDamageDecreaseApplyCount": 4,
            "param1": 1,
            "param2": 0,
            "shape": 67
          }
        },
        {
          "baseEffectId": 2,
          "className": "EffectInstanceDice",
          "delay": 0,
          "diceNum": 1,
          "diceSide": 0,
          "dispellable": 1,
          "displayZero": false,
          "duration": 0,
          "effectElement": -1,
          "effectId": 111,
          "effectTriggerDuration": 0,
          "effectUid": 0,
          "forClientOnly": false,
          "group": 0,
          "m_flags": 8,
          "modificator": 0,
          "order": 0,
          "random": 0,
          "spellId": -1,
          "targetId": 0,
          "targetMask": "",
          "trigger": false,
          "triggers": "",
          "value": 0,
          "visibleInBuffUi": false,
          "visibleInFightLog": false,
          "visibleInTooltip": false,
          "visibleOnTerrain": true,
          "zoneDescr": {
            "cellIds": [],
            "damageDecreaseStepPercent": 10,
            "isStopAtTarget": false,
            "maxDamageDecreaseApplyCount": 4,
            "param1": 1,
            "param2": 0,
            "shape": 67
          }
        },
        {
          "baseEffectId": 11,
          "className": "EffectInstanceDice",
          "delay": 0,
          "diceNum": 1,
          "diceSide": 0,
          "dispellable": 1,
          "displayZero": false,
          "duration": 0,
          "effectElement": -1,
          "effectId": 117,
          "effectTriggerDuration": 0,
          "effectUid": 0,
          "forClientOnly": false,
          "group": 0,
          "m_flags": 8,
          "modificator": 0,
          "order": 0,
          "random": 0,
          "spellId": -1,
          "targetId": 0,
          "targetMask": "",
          "trigger": false,
          "triggers": "",
          "value": 0,
          "visibleInBuffUi": false,
          "visibleInFightLog": false,
          "visibleInTooltip": false,
          "visibleOnTerrain": true,
          "zoneDescr": {
            "cellIds": [],
            "damageDecreaseStepPercent": 10,
            "isStopAtTarget": false,
            "maxDamageDecreaseApplyCount": 4,
            "param1": 1,
            "param2": 0,
            "shape": 67
          }
        }
      ]
    ],
    "slug": {
      "de": "gorgoyl-set",
      "en": "gorgoyle set",
      "es": "set de marranargola",
      "fr": "panoplie du gorgouille",
      "pt": "conjunto do gorgula"
    },
    "typeIds": [
      1,
      17,
      9,
      11
    ],
    "updatedAt": "2025-09-23T12:09:09.346Z"
  },
  "itemSetId": 215,
  "legendaryTreasureHuntThatReward": 0,
  "level": 97,
  "m_flags": 1092,
  "m_id": 12372,
  "name": {
    "de": "Gorgoyl-Handschuh",
    "en": "Gorgoyle Glove",
    "es": "Guantelete de marranárgola",
    "fr": "Gantelet du Gorgouille",
    "id": "37751",
    "pt": "Luva do Górgula"
  },
  "needUseConfirm": false,
  "nonUsableOnAnother": false,
  "possibleEffects": [
    {
      "baseEffectId": 5,
      "className": "EffectInstanceDice",
      "delay": 0,
      "diceNum": 41,
      "diceSide": 60,
      "dispellable": 1,
      "displayZero": false,
      "duration": 0,
      "effectElement": -1,
      "effectId": 125,
      "effectTriggerDuration": 0,
      "effectUid": 0,
      "forClientOnly": false,
      "group": 0,
      "m_flags": 15,
      "modificator": 0,
      "order": 0,
      "random": 0,
      "spellId": -1,
      "targetId": 0,
      "targetMask": "",
      "trigger": false,
      "triggers": "",
      "value": 0,
      "visibleInBuffUi": true,
      "visibleInFightLog": true,
      "visibleInTooltip": true,
      "visibleOnTerrain": true,
      "zoneDescr": {
        "cellIds": [],
        "damageDecreaseStepPercent": 10,
        "isStopAtTarget": false,
        "maxDamageDecreaseApplyCount": 4,
        "param1": 1,
        "param2": 0,
        "shape": 67
      }
    },
    {
      "baseEffectId": 6,
      "className": "EffectInstanceDice",
      "delay": 0,
      "diceNum": 11,
      "diceSide": 15,
      "dispellable": 1,
      "displayZero": false,
      "duration": 0,
      "effectElement": -1,
      "effectId": 124,
      "effectTriggerDuration": 0,
      "effectUid": 0,
      "forClientOnly": false,
      "group": 0,
      "m_flags": 15,
      "modificator": 0,
      "order": 0,
      "random": 0,
      "spellId": -1,
      "targetId": 0,
      "targetMask": "",
      "trigger": false,
      "triggers": "",
      "value": 0,
      "visibleInBuffUi": true,
      "visibleInFightLog": true,
      "visibleInTooltip": true,
      "visibleOnTerrain": true,
      "zoneDescr": {
        "cellIds": [],
        "damageDecreaseStepPercent": 10,
        "isStopAtTarget": false,
        "maxDamageDecreaseApplyCount": 4,
        "param1": 1,
        "param2": 0,
        "shape": 67
      }
    },
    {
      "baseEffectId": 22,
      "className": "EffectInstanceDice",
      "delay": 0,
      "diceNum": 21,
      "diceSide": 25,
      "dispellable": 1,
      "displayZero": false,
      "duration": 0,
      "effectElement": -1,
      "effectId": 138,
      "effectTriggerDuration": 0,
      "effectUid": 0,
      "forClientOnly": false,
      "group": 0,
      "m_flags": 15,
      "modificator": 0,
      "order": 0,
      "random": 0,
      "spellId": -1,
      "targetId": 0,
      "targetMask": "",
      "trigger": false,
      "triggers": "",
      "value": 0,
      "visibleInBuffUi": true,
      "visibleInFightLog": true,
      "visibleInTooltip": true,
      "visibleOnTerrain": true,
      "zoneDescr": {
        "cellIds": [],
        "damageDecreaseStepPercent": 10,
        "isStopAtTarget": false,
        "maxDamageDecreaseApplyCount": 4,
        "param1": 1,
        "param2": 0,
        "shape": 67
      }
    },
    {
      "baseEffectId": 23,
      "className": "EffectInstanceDice",
      "delay": 0,
      "diceNum": 1,
      "diceSide": 0,
      "dispellable": 1,
      "displayZero": false,
      "duration": 0,
      "effectElement": -1,
      "effectId": 182,
      "effectTriggerDuration": 0,
      "effectUid": 0,
      "forClientOnly": false,
      "group": 0,
      "m_flags": 15,
      "modificator": 0,
      "order": 0,
      "random": 0,
      "spellId": -1,
      "targetId": 0,
      "targetMask": "",
      "trigger": false,
      "triggers": "",
      "value": 0,
      "visibleInBuffUi": true,
      "visibleInFightLog": true,
      "visibleInTooltip": true,
      "visibleOnTerrain": true,
      "zoneDescr": {
        "cellIds": [],
        "damageDecreaseStepPercent": 10,
        "isStopAtTarget": false,
        "maxDamageDecreaseApplyCount": 4,
        "param1": 1,
        "param2": 0,
        "shape": 67
      }
    },
    {
      "baseEffectId": 374,
      "className": "EffectInstanceDice",
      "delay": 0,
      "diceNum": 2,
      "diceSide": 3,
      "dispellable": 1,
      "displayZero": false,
      "duration": 0,
      "effectElement": -1,
      "effectId": 430,
      "effectTriggerDuration": 0,
      "effectUid": 0,
      "forClientOnly": false,
      "group": 0,
      "m_flags": 15,
      "modificator": 0,
      "order": 0,
      "random": 0,
      "spellId": -1,
      "targetId": 0,
      "targetMask": "",
      "trigger": false,
      "triggers": "",
      "value": 0,
      "visibleInBuffUi": true,
      "visibleInFightLog": true,
      "visibleInTooltip": true,
      "visibleOnTerrain": true,
      "zoneDescr": {
        "cellIds": [],
        "damageDecreaseStepPercent": 10,
        "isStopAtTarget": false,
        "maxDamageDecreaseApplyCount": 4,
        "param1": 1,
        "param2": 0,
        "shape": 67
      }
    },
    {
      "baseEffectId": 365,
      "className": "EffectInstanceDice",
      "delay": 0,
      "diceNum": 2,
      "diceSide": 3,
      "dispellable": 1,
      "displayZero": false,
      "duration": 0,
      "effectElement": -1,
      "effectId": 422,
      "effectTriggerDuration": 0,
      "effectUid": 0,
      "forClientOnly": false,
      "group": 0,
      "m_flags": 15,
      "modificator": 0,
      "order": 0,
      "random": 0,
      "spellId": -1,
      "targetId": 0,
      "targetMask": "",
      "trigger": false,
      "triggers": "",
      "value": 0,
      "visibleInBuffUi": true,
      "visibleInFightLog": true,
      "visibleInTooltip": true,
      "visibleOnTerrain": true,
      "zoneDescr": {
        "cellIds": [],
        "damageDecreaseStepPercent": 10,
        "isStopAtTarget": false,
        "maxDamageDecreaseApplyCount": 4,
        "param1": 1,
        "param2": 0,
        "shape": 67
      }
    },
    {
      "baseEffectId": 368,
      "className": "EffectInstanceDice",
      "delay": 0,
      "diceNum": 2,
      "diceSide": 3,
      "dispellable": 1,
      "displayZero": false,
      "duration": 0,
      "effectElement": -1,
      "effectId": 424,
      "effectTriggerDuration": 0,
      "effectUid": 0,
      "forClientOnly": false,
      "group": 0,
      "m_flags": 15,
      "modificator": 0,
      "order": 0,
      "random": 0,
      "spellId": -1,
      "targetId": 0,
      "targetMask": "",
      "trigger": false,
      "triggers": "",
      "value": 0,
      "visibleInBuffUi": true,
      "visibleInFightLog": true,
      "visibleInTooltip": true,
      "visibleOnTerrain": true,
      "zoneDescr": {
        "cellIds": [],
        "damageDecreaseStepPercent": 10,
        "isStopAtTarget": false,
        "maxDamageDecreaseApplyCount": 4,
        "param1": 1,
        "param2": 0,
        "shape": 67
      }
    },
    {
      "baseEffectId": 344,
      "className": "EffectInstanceDice",
      "delay": 0,
      "diceNum": 2,
      "diceSide": 3,
      "dispellable": 1,
      "displayZero": false,
      "duration": 0,
      "effectElement": -1,
      "effectId": 753,
      "effectTriggerDuration": 0,
      "effectUid": 0,
      "forClientOnly": false,
      "group": 0,
      "m_flags": 15,
      "modificator": 0,
      "order": 0,
      "random": 0,
      "spellId": -1,
      "targetId": 0,
      "targetMask": "",
      "trigger": false,
      "triggers": "",
      "value": 0,
      "visibleInBuffUi": true,
      "visibleInFightLog": true,
      "visibleInTooltip": true,
      "visibleOnTerrain": true,
      "zoneDescr": {
        "cellIds": [],
        "damageDecreaseStepPercent": 10,
        "isStopAtTarget": false,
        "maxDamageDecreaseApplyCount": 4,
        "param1": 1,
        "param2": 0,
        "shape": 67
      }
    },
    {
      "baseEffectId": 355,
      "className": "EffectInstanceDice",
      "delay": 0,
      "diceNum": 2,
      "diceSide": 3,
      "dispellable": 1,
      "displayZero": false,
      "duration": 0,
      "effectElement": -1,
      "effectId": 412,
      "effectTriggerDuration": 0,
      "effectUid": 0,
      "forClientOnly": false,
      "group": 0,
      "m_flags": 15,
      "modificator": 0,
      "order": 0,
      "random": 0,
      "spellId": -1,
      "targetId": 0,
      "targetMask": "",
      "trigger": false,
      "triggers": "",
      "value": 0,
      "visibleInBuffUi": true,
      "visibleInFightLog": true,
      "visibleInTooltip": true,
      "visibleOnTerrain": true,
      "zoneDescr": {
        "cellIds": [],
        "damageDecreaseStepPercent": 10,
        "isStopAtTarget": false,
        "maxDamageDecreaseApplyCount": 4,
        "param1": 1,
        "param2": 0,
        "shape": 67
      }
    },
    {
      "baseEffectId": 357,
      "className": "EffectInstanceDice",
      "delay": 0,
      "diceNum": 2,
      "diceSide": 3,
      "dispellable": 1,
      "displayZero": false,
      "duration": 0,
      "effectElement": -1,
      "effectId": 414,
      "effectTriggerDuration": 0,
      "effectUid": 0,
      "forClientOnly": false,
      "group": 0,
      "m_flags": 15,
      "modificator": 0,
      "order": 0,
      "random": 0,
      "spellId": -1,
      "targetId": 0,
      "targetMask": "",
      "trigger": false,
      "triggers": "",
      "value": 0,
      "visibleInBuffUi": true,
      "visibleInFightLog": true,
      "visibleInTooltip": true,
      "visibleOnTerrain": true,
      "zoneDescr": {
        "cellIds": [],
        "damageDecreaseStepPercent": 10,
        "isStopAtTarget": false,
        "maxDamageDecreaseApplyCount": 4,
        "param1": 1,
        "param2": 0,
        "shape": 67
      }
    }
  ],
  "price": 9700,
  "questsThatReward": [],
  "questsThatUse": [],
  "realWeight": 10,
  "recipeIds": [],
  "recipeSlots": 6,
  "recipesThatUse": [],
  "recyclingNuggets": 0,
  "resourcesBySubarea": [],
  "secretRecipe": false,
  "slug": {
    "de": "gorgoyl-handschuh",
    "en": "gorgoyle glove",
    "es": "guantelete de marranargola",
    "fr": "gantelet du gorgouille",
    "pt": "luva do gorgula"
  },
  "startLegendaryTreasureHunt": 0,
  "targetable": false,
  "twoHanded": false,
  "type": {
    "_id": "674e524064788cc74141840c",
    "categoryId": 0,
    "className": "ItemTypeData",
    "craftXpRatio": -1,
    "createdAt": "2024-12-03T00:35:12.568Z",
    "evolutiveTypeId": 0,
    "id": 9,
    "isInEncyclopedia": true,
    "m_id": 9,
    "name": {
      "de": "Ring",
      "en": "Ring",
      "es": "Anillo",
      "fr": "Anneau",
      "id": "29696",
      "pt": "Anel"
    },
    "rawZone": "",
    "superType": {
      "_id": "60abc386a664687005dfd1bc",
      "className": "ItemSuperTypeData",
      "createdAt": "2021-05-24T15:16:28.560Z",
      "id": 3,
      "m_id": 3,
      "name": {
        "de": "Ring",
        "en": "Ring",
        "es": "Anillo",
        "fr": "Anneau",
        "pt": "Anel"
      },
      "positions": [
        2,
        4
      ],
      "updatedAt": "2025-09-23T12:09:10.064Z"
    },
    "superTypeId": 3,
    "updatedAt": "2025-09-23T12:09:10.305Z"
  },
  "typeId": 9,
  "updatedAt": "2025-09-23T12:09:25.271Z",
  "usable": false,
  "visibilityCriterion": ""
}