{
  "_id": "674e524064788cc74141989d",
  "achievementsThatReward": [],
  "appearanceId": 0,
  "castInDiagonal": false,
  "castInLine": false,
  "castTestLos": false,
  "className": "ItemData",
  "craftConditionalCriterion": "",
  "craftFeasibleCriterion": "",
  "craftVisibleCriterion": "",
  "craftXpRatio": -1,
  "createdAt": "2024-12-03T00:35:12.820Z",
  "criterions": "",
  "criterionsTarget": "",
  "description": {
    "de": "Dieser Ti-Ping sträubt sich gegen die Adoption und wird sich bei der der erstbesten Gelegenheit auf und davon machen. Bis dahin könnt ihr mit ihm aber noch ein wenig bei euren Freunden herumprotzen.",
    "en": "This Pingwinkle doesn't like being adopted and will flee at the first opportunity. In the meantime, you can show it to your friends for them to abuse.",
    "es": "A este pekegüino no le gusta la adopción y se escapará en cuanto pueda. Pero antes se lo puedes enseñar a tus amigos para que se rían de él.",
    "fr": "Ce timansot n'aime pas l'adoption et s'enfuira à la première occasion. En attendant, vous pouvez le montrer à vos amis pour qu'ils le maltraitent.",
    "id": "38390",
    "pt": "Este Pekegwin não gosta de ser adotado e fugirá na primeira oportunidade. Enquanto isso, você pode mostrá-lo para seus amigos a fim de que eles abusem da bondade dele."
  },
  "dropMonsterIds": [],
  "dropSubAreaIds": [],
  "dropTemporisMonsterIds": [],
  "effects": [
    {
      "category": 0,
      "characteristic": 48,
      "effectId": 176,
      "elementId": -1,
      "from": 10,
      "to": 0
    }
  ],
  "enhanceable": true,
  "etheral": false,
  "evolutiveEffectIds": [],
  "exchangeable": true,
  "favoriteRecyclingSubareas": [],
  "favoriteSubAreas": [],
  "favoriteSubAreasBonus": 0,
  "hasLivingObjectSkinJntMood": false,
  "hasRecipe": false,
  "hideEffects": false,
  "iconId": 32036,
  "id": 11277,
  "img": "https://api.dofusdb.fr/img/items/32036.png",
  "importantNotice": {
    "id": "0"
  },
  "isColorable": false,
  "isLegendary": false,
  "isSaleable": true,
  "itemSet": false,
  "itemSetId": -1,
  "legendaryTreasureHuntThatReward": 0,
  "level": 1,
  "m_flags": 1092,
  "m_id": 11277,
  "name": {
    "de": "Streunender Ti-Ping",
    "en": "Rascally Pingwinkle",
    "es": "Pekegüino pillo",
    "fr": "Timansot chenapan",
    "id": "38389",
    "pt": "Pekegwin travesso"
  },
  "needUseConfirm": false,
  "nonUsableOnAnother": false,
  "possibleEffects": [
    {
      "baseEffectId": 92,
      "className": "EffectInstanceDice",
      "delay": 0,
      "diceNum": 2,
      "diceSide": 0,
      "dispellable": 1,
      "displayZero": false,
      "duration": 0,
      "effectElement": -1,
      "effectId": 148,
      "effectTriggerDuration": 0,
      "effectUid": 0,
      "forClientOnly": false,
      "group": 0,
      "m_flags": 15,
      "modificator": 0,
      "order": 0,
      "random": 0,
      "spellId": -1,
      "targetId": 0,
      "targetMask": "",
      "trigger": false,
      "triggers": "",
      "value": 2849,
      "visibleInBuffUi": true,
      "visibleInFightLog": true,
      "visibleInTooltip": true,
      "visibleOnTerrain": true,
      "zoneDescr": {
        "cellIds": [],
        "damageDecreaseStepPercent": 10,
        "isStopAtTarget": false,
        "maxDamageDecreaseApplyCount": 4,
        "param1": 1,
        "param2": 0,
        "shape": 67
      }
    },
    {
      "baseEffectId": 106,
      "className": "EffectInstanceDice",
      "delay": 0,
      "diceNum": 10,
      "diceSide": 0,
      "dispellable": 1,
      "displayZero": false,
      "duration": 0,
      "effectElement": -1,
      "effectId": 176,
      "effectTriggerDuration": 0,
      "effectUid": 0,
      "forClientOnly": false,
      "group": 0,
      "m_flags": 15,
      "modificator": 0,
      "order": 0,
      "random": 0,
      "spellId": -1,
      "targetId": 0,
      "targetMask": "",
      "trigger": false,
      "triggers": "",
      "value": 0,
      "visibleInBuffUi": true,
      "visibleInFightLog": true,
      "visibleInTooltip": true,
      "visibleOnTerrain": true,
      "zoneDescr": {
        "cellIds": [],
        "damageDecreaseStepPercent": 10,
        "isStopAtTarget": false,
        "maxDamageDecreaseApplyCount": 4,
        "param1": 1,
        "param2": 0,
        "shape": 67
      }
    },
    {
      "baseEffectId": 83,
      "className": "EffectInstanceDice",
      "delay": 0,
      "diceNum": 0,
      "diceSide": 0,
      "dispellable": 1,
      "displayZero": false,
      "duration": 0,
      "effectElement": -1,
      "effectId": 811,
      "effectTriggerDuration": 0,
      "effectUid": 0,
      "forClientOnly": false,
      "group": 0,
      "m_flags": 15,
      "modificator": 0,
      "order": 0,
      "random": 0,
      "spellId": -1,
      "targetId": 0,
      "targetMask": "",
      "trigger": false,
      "triggers": "",
      "value": 3,
      "visibleInBuffUi": true,
      "visibleInFightLog": true,
      "visibleInTooltip": true,
      "visibleOnTerrain": true,
      "zoneDescr": {
        "cellIds": [],
        "damageDecreaseStepPercent": 10,
        "isStopAtTarget": false,
        "maxDamageDecreaseApplyCount": 4,
        "param1": 1,
        "param2": 0,
        "shape": 67
      }
    }
  ],
  "price": 1,
  "questsThatReward": [
    584
  ],
  "questsThatUse": [],
  "realWeight": 0,
  "recipeIds": [],
  "recipeSlots": 0,
  "recipesThatUse": [],
  "recyclingNuggets": 0,
  "resourcesBySubarea": [],
  "secretRecipe": false,
  "slug": {
    "de": "streunender ti-ping",
    "en": "rascally pingwinkle",
    "es": "pekeguino pillo",
    "fr": "timansot chenapan",
    "pt": "pekegwin travesso"
  },
  "startLegendaryTreasureHunt": 0,
  "targetable": false,
  "twoHanded": false,
  "type": {
    "_id": "674e524064788cc741418421",
    "categoryId": 4,
    "className": "ItemTypeData",
    "craftXpRatio": -1,
    "createdAt": "2024-12-03T00:35:12.568Z",
    "evolutiveTypeId": 0,
    "id": 30,
    "isInEncyclopedia": false,
    "m_id": 30,
    "name": {
      "de": "Fluch",
      "en": "Curse",
      "es": "Maldición",
      "fr": "Malédiction",
      "id": "29738",
      "pt": "Maldição"
    },
    "rawZone": "",
    "superType": {
      "_id": "60abc52fa664687005dfd1cb",
      "className": "ItemSuperTypeData",
      "createdAt": "2021-05-24T15:16:28.560Z",
      "id": 18,
      "m_id": 18,
      "name": {
        "de": "Fluch",
        "en": "Curse",
        "es": "Maldición",
        "fr": "Malédiction",
        "pt": "Maldição"
      },
      "positions": [
        24,
        25
      ],
      "updatedAt": "2025-09-23T12:09:10.066Z"
    },
    "superTypeId": 18,
    "updatedAt": "2025-09-23T12:09:10.311Z"
  },
  "typeId": 30,
  "updatedAt": "2025-09-23T12:09:24.993Z",
  "usable": false,
  "visibilityCriterion": ""
}