{
  "_id": "674e524064788cc741419204",
  "achievementsThatReward": [],
  "apCost": 4,
  "appearanceId": 0,
  "castInDiagonal": false,
  "castInLine": false,
  "castTestLos": true,
  "className": "WeaponData",
  "craftConditionalCriterion": "",
  "craftFeasibleCriterion": "SC!5|ST!5",
  "craftVisibleCriterion": "SC!5|ST!5",
  "craftXpRatio": -1,
  "createdAt": "2024-12-03T00:35:12.820Z",
  "criterions": "",
  "criterionsTarget": "",
  "criticalHitBonus": 5,
  "criticalHitProbability": 30,
  "description": {
    "de": "Mit diesem Ast pflegte der helle Astakrachler die für ihn schwer zugänglichen Körperteile zu kraulen. Da der Ast nicht nachbehandelt wurde, könnt ihr aus seinem Geruch schließen, welches Körperteil dabei wohl am meisten strapaziert wurde.",
    "en": "This branch was apparently used to scrape some otherwise inaccessible body part. This might explain the stick's stickiness.",
    "es": "Con esta rama, el abrajidor se rascaba ciertas partes del cuerpo difícilmente accesibles. Esto explica ese extraño olor que tiene.",
    "fr": "Cette branche servait à racler certaines parties du corps inaccessibles autrement. Ceci explique peut-être l'odeur étrange de cette branche.",
    "id": "46130",
    "pt": "Este galho foi usado para esfregar algumas partes do corpo antes inacessíveis. Isso talvez explique o cheiro estranho..."
  },
  "dropMonsterIds": [],
  "dropSubAreaIds": [],
  "dropTemporisMonsterIds": [],
  "effects": [
    {
      "category": 2,
      "characteristic": -1,
      "effectId": 100,
      "elementId": 0,
      "from": 7,
      "to": 16
    },
    {
      "category": 2,
      "characteristic": -1,
      "effectId": 98,
      "elementId": 4,
      "from": 7,
      "to": 16
    },
    {
      "category": 2,
      "characteristic": -1,
      "effectId": 92,
      "elementId": 1,
      "from": 4,
      "to": 6
    },
    {
      "category": 0,
      "characteristic": 11,
      "effectId": 125,
      "elementId": -1,
      "from": 101,
      "to": 150
    },
    {
      "category": 0,
      "characteristic": 10,
      "effectId": 118,
      "elementId": 1,
      "from": 26,
      "to": 40
    },
    {
      "category": 0,
      "characteristic": 14,
      "effectId": 119,
      "elementId": 4,
      "from": 26,
      "to": 40
    },
    {
      "category": 0,
      "characteristic": 12,
      "effectId": 124,
      "elementId": -1,
      "from": 26,
      "to": 40
    },
    {
      "category": 0,
      "characteristic": 48,
      "effectId": 176,
      "elementId": -1,
      "from": 11,
      "to": 15
    },
    {
      "category": 1,
      "characteristic": 37,
      "effectId": 214,
      "elementId": -1,
      "from": 6,
      "to": 8
    },
    {
      "category": 1,
      "characteristic": 36,
      "effectId": 212,
      "elementId": -1,
      "from": 6,
      "to": 8
    }
  ],
  "enhanceable": true,
  "etheral": false,
  "evolutiveEffectIds": [],
  "exchangeable": true,
  "favoriteRecyclingSubareas": [],
  "favoriteSubAreas": [],
  "favoriteSubAreasBonus": 0,
  "hasLivingObjectSkinJntMood": false,
  "hasRecipe": true,
  "hideEffects": false,
  "iconId": 3065,
  "id": 8835,
  "img": "https://api.dofusdb.fr/img/items/3065.png",
  "importantNotice": {
    "id": "0"
  },
  "isColorable": false,
  "isLegendary": false,
  "isSaleable": true,
  "itemSet": {
    "_id": "674e523f64788cc74141811c",
    "bonusIsSecret": false,
    "className": "ItemSetData",
    "createdAt": "2024-12-03T00:35:11.399Z",
    "effects": [
      [],
      [
        {
          "category": 0,
          "characteristic": 10,
          "effectId": 118,
          "elementId": 1,
          "from": 30,
          "to": 0
        },
        {
          "category": 0,
          "characteristic": 14,
          "effectId": 119,
          "elementId": 4,
          "from": 30,
          "to": 0
        },
        {
          "category": 0,
          "characteristic": 91,
          "effectId": 428,
          "elementId": 4,
          "from": 8,
          "to": 0
        },
        {
          "category": 0,
          "characteristic": 88,
          "effectId": 422,
          "elementId": 1,
          "from": 8,
          "to": 0
        },
        {
          "category": 0,
          "characteristic": 92,
          "effectId": 430,
          "elementId": 0,
          "from": 8,
          "to": 0
        }
      ],
      [
        {
          "category": 0,
          "characteristic": 1,
          "effectId": 111,
          "elementId": -1,
          "from": 1,
          "to": 0
        },
        {
          "category": 0,
          "characteristic": 91,
          "effectId": 428,
          "elementId": 4,
          "from": 8,
          "to": 0
        },
        {
          "category": 0,
          "characteristic": 88,
          "effectId": 422,
          "elementId": 1,
          "from": 8,
          "to": 0
        },
        {
          "category": 0,
          "characteristic": 92,
          "effectId": 430,
          "elementId": 0,
          "from": 8,
          "to": 0
        },
        {
          "category": 0,
          "characteristic": 14,
          "effectId": 119,
          "elementId": 4,
          "from": 30,
          "to": 0
        },
        {
          "category": 0,
          "characteristic": 10,
          "effectId": 118,
          "elementId": 1,
          "from": 30,
          "to": 0
        }
      ],
      [
        {
          "category": 0,
          "characteristic": 1,
          "effectId": 111,
          "elementId": -1,
          "from": 1,
          "to": 0
        },
        {
          "category": 0,
          "characteristic": 19,
          "effectId": 117,
          "elementId": -1,
          "from": 1,
          "to": 0
        },
        {
          "category": 0,
          "characteristic": 91,
          "effectId": 428,
          "elementId": 4,
          "from": 8,
          "to": 0
        },
        {
          "category": 0,
          "characteristic": 88,
          "effectId": 422,
          "elementId": 1,
          "from": 8,
          "to": 0
        },
        {
          "category": 0,
          "characteristic": 92,
          "effectId": 430,
          "elementId": 0,
          "from": 8,
          "to": 0
        },
        {
          "category": 0,
          "characteristic": 14,
          "effectId": 119,
          "elementId": 4,
          "from": 30,
          "to": 0
        },
        {
          "category": 0,
          "characteristic": 10,
          "effectId": 118,
          "elementId": 1,
          "from": 30,
          "to": 0
        }
      ]
    ],
    "id": 79,
    "isCosmetic": false,
    "items": [
      8822,
      8835,
      8869,
      8871
    ],
    "level": 135,
    "m_id": 79,
    "name": {
      "de": "Licht-Set",
      "en": "Light Set",
      "es": "Set del abrajidor claro",
      "fr": "Panoplie Claire",
      "id": "59997",
      "pt": "Conjunto Claro"
    },
    "possibleEffects": [
      [],
      [
        {
          "baseEffectId": 4,
          "className": "EffectInstanceDice",
          "delay": 0,
          "diceNum": 30,
          "diceSide": 0,
          "dispellable": 1,
          "displayZero": false,
          "duration": 0,
          "effectElement": -1,
          "effectId": 118,
          "effectTriggerDuration": 0,
          "effectUid": 0,
          "forClientOnly": false,
          "group": 0,
          "m_flags": 8,
          "modificator": 0,
          "order": 0,
          "random": 0,
          "spellId": -1,
          "targetId": 0,
          "targetMask": "",
          "trigger": false,
          "triggers": "",
          "value": 0,
          "visibleInBuffUi": false,
          "visibleInFightLog": false,
          "visibleInTooltip": false,
          "visibleOnTerrain": true,
          "zoneDescr": {
            "cellIds": [],
            "damageDecreaseStepPercent": 10,
            "isStopAtTarget": false,
            "maxDamageDecreaseApplyCount": 4,
            "param1": 1,
            "param2": 0,
            "shape": 67
          }
        },
        {
          "baseEffectId": 8,
          "className": "EffectInstanceDice",
          "delay": 0,
          "diceNum": 30,
          "diceSide": 0,
          "dispellable": 1,
          "displayZero": false,
          "duration": 0,
          "effectElement": -1,
          "effectId": 119,
          "effectTriggerDuration": 0,
          "effectUid": 0,
          "forClientOnly": false,
          "group": 0,
          "m_flags": 8,
          "modificator": 0,
          "order": 0,
          "random": 0,
          "spellId": -1,
          "targetId": 0,
          "targetMask": "",
          "trigger": false,
          "triggers": "",
          "value": 0,
          "visibleInBuffUi": false,
          "visibleInFightLog": false,
          "visibleInTooltip": false,
          "visibleOnTerrain": true,
          "zoneDescr": {
            "cellIds": [],
            "damageDecreaseStepPercent": 10,
            "isStopAtTarget": false,
            "maxDamageDecreaseApplyCount": 4,
            "param1": 1,
            "param2": 0,
            "shape": 67
          }
        },
        {
          "baseEffectId": 372,
          "className": "EffectInstanceDice",
          "delay": 0,
          "diceNum": 8,
          "diceSide": 0,
          "dispellable": 1,
          "displayZero": false,
          "duration": 0,
          "effectElement": -1,
          "effectId": 428,
          "effectTriggerDuration": 0,
          "effectUid": 0,
          "forClientOnly": false,
          "group": 0,
          "m_flags": 8,
          "modificator": 0,
          "order": 0,
          "random": 0,
          "spellId": -1,
          "targetId": 0,
          "targetMask": "",
          "trigger": false,
          "triggers": "",
          "value": 0,
          "visibleInBuffUi": false,
          "visibleInFightLog": false,
          "visibleInTooltip": false,
          "visibleOnTerrain": true,
          "zoneDescr": {
            "cellIds": [],
            "damageDecreaseStepPercent": 10,
            "isStopAtTarget": false,
            "maxDamageDecreaseApplyCount": 4,
            "param1": 1,
            "param2": 0,
            "shape": 67
          }
        },
        {
          "baseEffectId": 365,
          "className": "EffectInstanceDice",
          "delay": 0,
          "diceNum": 8,
          "diceSide": 0,
          "dispellable": 1,
          "displayZero": false,
          "duration": 0,
          "effectElement": -1,
          "effectId": 422,
          "effectTriggerDuration": 0,
          "effectUid": 0,
          "forClientOnly": false,
          "group": 0,
          "m_flags": 8,
          "modificator": 0,
          "order": 0,
          "random": 0,
          "spellId": -1,
          "targetId": 0,
          "targetMask": "",
          "trigger": false,
          "triggers": "",
          "value": 0,
          "visibleInBuffUi": false,
          "visibleInFightLog": false,
          "visibleInTooltip": false,
          "visibleOnTerrain": true,
          "zoneDescr": {
            "cellIds": [],
            "damageDecreaseStepPercent": 10,
            "isStopAtTarget": false,
            "maxDamageDecreaseApplyCount": 4,
            "param1": 1,
            "param2": 0,
            "shape": 67
          }
        },
        {
          "baseEffectId": 374,
          "className": "EffectInstanceDice",
          "delay": 0,
          "diceNum": 8,
          "diceSide": 0,
          "dispellable": 1,
          "displayZero": false,
          "duration": 0,
          "effectElement": -1,
          "effectId": 430,
          "effectTriggerDuration": 0,
          "effectUid": 0,
          "forClientOnly": false,
          "group": 0,
          "m_flags": 8,
          "modificator": 0,
          "order": 0,
          "random": 0,
          "spellId": -1,
          "targetId": 0,
          "targetMask": "",
          "trigger": false,
          "triggers": "",
          "value": 0,
          "visibleInBuffUi": false,
          "visibleInFightLog": false,
          "visibleInTooltip": false,
          "visibleOnTerrain": true,
          "zoneDescr": {
            "cellIds": [],
            "damageDecreaseStepPercent": 10,
            "isStopAtTarget": false,
            "maxDamageDecreaseApplyCount": 4,
            "param1": 1,
            "param2": 0,
            "shape": 67
          }
        }
      ],
      [
        {
          "baseEffectId": 2,
          "className": "EffectInstanceDice",
          "delay": 0,
          "diceNum": 1,
          "diceSide": 0,
          "dispellable": 1,
          "displayZero": false,
          "duration": 0,
          "effectElement": -1,
          "effectId": 111,
          "effectTriggerDuration": 0,
          "effectUid": 0,
          "forClientOnly": false,
          "group": 0,
          "m_flags": 8,
          "modificator": 0,
          "order": 0,
          "random": 0,
          "spellId": -1,
          "targetId": 0,
          "targetMask": "",
          "trigger": false,
          "triggers": "",
          "value": 0,
          "visibleInBuffUi": false,
          "visibleInFightLog": false,
          "visibleInTooltip": false,
          "visibleOnTerrain": true,
          "zoneDescr": {
            "cellIds": [],
            "damageDecreaseStepPercent": 10,
            "isStopAtTarget": false,
            "maxDamageDecreaseApplyCount": 4,
            "param1": 1,
            "param2": 0,
            "shape": 67
          }
        },
        {
          "baseEffectId": 372,
          "className": "EffectInstanceDice",
          "delay": 0,
          "diceNum": 8,
          "diceSide": 0,
          "dispellable": 1,
          "displayZero": false,
          "duration": 0,
          "effectElement": -1,
          "effectId": 428,
          "effectTriggerDuration": 0,
          "effectUid": 0,
          "forClientOnly": false,
          "group": 0,
          "m_flags": 8,
          "modificator": 0,
          "order": 0,
          "random": 0,
          "spellId": -1,
          "targetId": 0,
          "targetMask": "",
          "trigger": false,
          "triggers": "",
          "value": 0,
          "visibleInBuffUi": false,
          "visibleInFightLog": false,
          "visibleInTooltip": false,
          "visibleOnTerrain": true,
          "zoneDescr": {
            "cellIds": [],
            "damageDecreaseStepPercent": 10,
            "isStopAtTarget": false,
            "maxDamageDecreaseApplyCount": 4,
            "param1": 1,
            "param2": 0,
            "shape": 67
          }
        },
        {
          "baseEffectId": 365,
          "className": "EffectInstanceDice",
          "delay": 0,
          "diceNum": 8,
          "diceSide": 0,
          "dispellable": 1,
          "displayZero": false,
          "duration": 0,
          "effectElement": -1,
          "effectId": 422,
          "effectTriggerDuration": 0,
          "effectUid": 0,
          "forClientOnly": false,
          "group": 0,
          "m_flags": 8,
          "modificator": 0,
          "order": 0,
          "random": 0,
          "spellId": -1,
          "targetId": 0,
          "targetMask": "",
          "trigger": false,
          "triggers": "",
          "value": 0,
          "visibleInBuffUi": false,
          "visibleInFightLog": false,
          "visibleInTooltip": false,
          "visibleOnTerrain": true,
          "zoneDescr": {
            "cellIds": [],
            "damageDecreaseStepPercent": 10,
            "isStopAtTarget": false,
            "maxDamageDecreaseApplyCount": 4,
            "param1": 1,
            "param2": 0,
            "shape": 67
          }
        },
        {
          "baseEffectId": 374,
          "className": "EffectInstanceDice",
          "delay": 0,
          "diceNum": 8,
          "diceSide": 0,
          "dispellable": 1,
          "displayZero": false,
          "duration": 0,
          "effectElement": -1,
          "effectId": 430,
          "effectTriggerDuration": 0,
          "effectUid": 0,
          "forClientOnly": false,
          "group": 0,
          "m_flags": 8,
          "modificator": 0,
          "order": 0,
          "random": 0,
          "spellId": -1,
          "targetId": 0,
          "targetMask": "",
          "trigger": false,
          "triggers": "",
          "value": 0,
          "visibleInBuffUi": false,
          "visibleInFightLog": false,
          "visibleInTooltip": false,
          "visibleOnTerrain": true,
          "zoneDescr": {
            "cellIds": [],
            "damageDecreaseStepPercent": 10,
            "isStopAtTarget": false,
            "maxDamageDecreaseApplyCount": 4,
            "param1": 1,
            "param2": 0,
            "shape": 67
          }
        },
        {
          "baseEffectId": 8,
          "className": "EffectInstanceDice",
          "delay": 0,
          "diceNum": 30,
          "diceSide": 0,
          "dispellable": 1,
          "displayZero": false,
          "duration": 0,
          "effectElement": -1,
          "effectId": 119,
          "effectTriggerDuration": 0,
          "effectUid": 0,
          "forClientOnly": false,
          "group": 0,
          "m_flags": 8,
          "modificator": 0,
          "order": 0,
          "random": 0,
          "spellId": -1,
          "targetId": 0,
          "targetMask": "",
          "trigger": false,
          "triggers": "",
          "value": 0,
          "visibleInBuffUi": false,
          "visibleInFightLog": false,
          "visibleInTooltip": false,
          "visibleOnTerrain": true,
          "zoneDescr": {
            "cellIds": [],
            "damageDecreaseStepPercent": 10,
            "isStopAtTarget": false,
            "maxDamageDecreaseApplyCount": 4,
            "param1": 1,
            "param2": 0,
            "shape": 67
          }
        },
        {
          "baseEffectId": 4,
          "className": "EffectInstanceDice",
          "delay": 0,
          "diceNum": 30,
          "diceSide": 0,
          "dispellable": 1,
          "displayZero": false,
          "duration": 0,
          "effectElement": -1,
          "effectId": 118,
          "effectTriggerDuration": 0,
          "effectUid": 0,
          "forClientOnly": false,
          "group": 0,
          "m_flags": 8,
          "modificator": 0,
          "order": 0,
          "random": 0,
          "spellId": -1,
          "targetId": 0,
          "targetMask": "",
          "trigger": false,
          "triggers": "",
          "value": 0,
          "visibleInBuffUi": false,
          "visibleInFightLog": false,
          "visibleInTooltip": false,
          "visibleOnTerrain": true,
          "zoneDescr": {
            "cellIds": [],
            "damageDecreaseStepPercent": 10,
            "isStopAtTarget": false,
            "maxDamageDecreaseApplyCount": 4,
            "param1": 1,
            "param2": 0,
            "shape": 67
          }
        }
      ],
      [
        {
          "baseEffectId": 2,
          "className": "EffectInstanceDice",
          "delay": 0,
          "diceNum": 1,
          "diceSide": 0,
          "dispellable": 1,
          "displayZero": false,
          "duration": 0,
          "effectElement": -1,
          "effectId": 111,
          "effectTriggerDuration": 0,
          "effectUid": 0,
          "forClientOnly": false,
          "group": 0,
          "m_flags": 8,
          "modificator": 0,
          "order": 0,
          "random": 0,
          "spellId": -1,
          "targetId": 0,
          "targetMask": "",
          "trigger": false,
          "triggers": "",
          "value": 0,
          "visibleInBuffUi": false,
          "visibleInFightLog": false,
          "visibleInTooltip": false,
          "visibleOnTerrain": true,
          "zoneDescr": {
            "cellIds": [],
            "damageDecreaseStepPercent": 10,
            "isStopAtTarget": false,
            "maxDamageDecreaseApplyCount": 4,
            "param1": 1,
            "param2": 0,
            "shape": 67
          }
        },
        {
          "baseEffectId": 11,
          "className": "EffectInstanceDice",
          "delay": 0,
          "diceNum": 1,
          "diceSide": 0,
          "dispellable": 1,
          "displayZero": false,
          "duration": 0,
          "effectElement": -1,
          "effectId": 117,
          "effectTriggerDuration": 0,
          "effectUid": 0,
          "forClientOnly": false,
          "group": 0,
          "m_flags": 8,
          "modificator": 0,
          "order": 0,
          "random": 0,
          "spellId": -1,
          "targetId": 0,
          "targetMask": "",
          "trigger": false,
          "triggers": "",
          "value": 0,
          "visibleInBuffUi": false,
          "visibleInFightLog": false,
          "visibleInTooltip": false,
          "visibleOnTerrain": true,
          "zoneDescr": {
            "cellIds": [],
            "damageDecreaseStepPercent": 10,
            "isStopAtTarget": false,
            "maxDamageDecreaseApplyCount": 4,
            "param1": 1,
            "param2": 0,
            "shape": 67
          }
        },
        {
          "baseEffectId": 372,
          "className": "EffectInstanceDice",
          "delay": 0,
          "diceNum": 8,
          "diceSide": 0,
          "dispellable": 1,
          "displayZero": false,
          "duration": 0,
          "effectElement": -1,
          "effectId": 428,
          "effectTriggerDuration": 0,
          "effectUid": 0,
          "forClientOnly": false,
          "group": 0,
          "m_flags": 8,
          "modificator": 0,
          "order": 0,
          "random": 0,
          "spellId": -1,
          "targetId": 0,
          "targetMask": "",
          "trigger": false,
          "triggers": "",
          "value": 0,
          "visibleInBuffUi": false,
          "visibleInFightLog": false,
          "visibleInTooltip": false,
          "visibleOnTerrain": true,
          "zoneDescr": {
            "cellIds": [],
            "damageDecreaseStepPercent": 10,
            "isStopAtTarget": false,
            "maxDamageDecreaseApplyCount": 4,
            "param1": 1,
            "param2": 0,
            "shape": 67
          }
        },
        {
          "baseEffectId": 365,
          "className": "EffectInstanceDice",
          "delay": 0,
          "diceNum": 8,
          "diceSide": 0,
          "dispellable": 1,
          "displayZero": false,
          "duration": 0,
          "effectElement": -1,
          "effectId": 422,
          "effectTriggerDuration": 0,
          "effectUid": 0,
          "forClientOnly": false,
          "group": 0,
          "m_flags": 8,
          "modificator": 0,
          "order": 0,
          "random": 0,
          "spellId": -1,
          "targetId": 0,
          "targetMask": "",
          "trigger": false,
          "triggers": "",
          "value": 0,
          "visibleInBuffUi": false,
          "visibleInFightLog": false,
          "visibleInTooltip": false,
          "visibleOnTerrain": true,
          "zoneDescr": {
            "cellIds": [],
            "damageDecreaseStepPercent": 10,
            "isStopAtTarget": false,
            "maxDamageDecreaseApplyCount": 4,
            "param1": 1,
            "param2": 0,
            "shape": 67
          }
        },
        {
          "baseEffectId": 374,
          "className": "EffectInstanceDice",
          "delay": 0,
          "diceNum": 8,
          "diceSide": 0,
          "dispellable": 1,
          "displayZero": false,
          "duration": 0,
          "effectElement": -1,
          "effectId": 430,
          "effectTriggerDuration": 0,
          "effectUid": 0,
          "forClientOnly": false,
          "group": 0,
          "m_flags": 8,
          "modificator": 0,
          "order": 0,
          "random": 0,
          "spellId": -1,
          "targetId": 0,
          "targetMask": "",
          "trigger": false,
          "triggers": "",
          "value": 0,
          "visibleInBuffUi": false,
          "visibleInFightLog": false,
          "visibleInTooltip": false,
          "visibleOnTerrain": true,
          "zoneDescr": {
            "cellIds": [],
            "damageDecreaseStepPercent": 10,
            "isStopAtTarget": false,
            "maxDamageDecreaseApplyCount": 4,
            "param1": 1,
            "param2": 0,
            "shape": 67
          }
        },
        {
          "baseEffectId": 8,
          "className": "EffectInstanceDice",
          "delay": 0,
          "diceNum": 30,
          "diceSide": 0,
          "dispellable": 1,
          "displayZero": false,
          "duration": 0,
          "effectElement": -1,
          "effectId": 119,
          "effectTriggerDuration": 0,
          "effectUid": 0,
          "forClientOnly": false,
          "group": 0,
          "m_flags": 8,
          "modificator": 0,
          "order": 0,
          "random": 0,
          "spellId": -1,
          "targetId": 0,
          "targetMask": "",
          "trigger": false,
          "triggers": "",
          "value": 0,
          "visibleInBuffUi": false,
          "visibleInFightLog": false,
          "visibleInTooltip": false,
          "visibleOnTerrain": true,
          "zoneDescr": {
            "cellIds": [],
            "damageDecreaseStepPercent": 10,
            "isStopAtTarget": false,
            "maxDamageDecreaseApplyCount": 4,
            "param1": 1,
            "param2": 0,
            "shape": 67
          }
        },
        {
          "baseEffectId": 4,
          "className": "EffectInstanceDice",
          "delay": 0,
          "diceNum": 30,
          "diceSide": 0,
          "dispellable": 1,
          "displayZero": false,
          "duration": 0,
          "effectElement": -1,
          "effectId": 118,
          "effectTriggerDuration": 0,
          "effectUid": 0,
          "forClientOnly": false,
          "group": 0,
          "m_flags": 8,
          "modificator": 0,
          "order": 0,
          "random": 0,
          "spellId": -1,
          "targetId": 0,
          "targetMask": "",
          "trigger": false,
          "triggers": "",
          "value": 0,
          "visibleInBuffUi": false,
          "visibleInFightLog": false,
          "visibleInTooltip": false,
          "visibleOnTerrain": true,
          "zoneDescr": {
            "cellIds": [],
            "damageDecreaseStepPercent": 10,
            "isStopAtTarget": false,
            "maxDamageDecreaseApplyCount": 4,
            "param1": 1,
            "param2": 0,
            "shape": 67
          }
        }
      ]
    ],
    "slug": {
      "de": "licht-set",
      "en": "light set",
      "es": "set del abrajidor claro",
      "fr": "panoplie claire",
      "pt": "conjunto claro"
    },
    "typeIds": [
      16,
      3,
      11,
      10
    ],
    "updatedAt": "2025-09-23T12:09:09.314Z"
  },
  "itemSetId": 79,
  "legendaryTreasureHuntThatReward": 0,
  "level": 132,
  "m_flags": 1092,
  "m_id": 8835,
  "maxCastPerTurn": 1,
  "minRange": 2,
  "name": {
    "de": "Ast des hellen Astakrachler",
    "en": "Light Treeckler Branch",
    "es": "Rama de abrajidor claro",
    "fr": "Branche de l'Abrakleur clair",
    "id": "46129",
    "pt": "Galho do Arvorador Claro"
  },
  "needUseConfirm": false,
  "nonUsableOnAnother": false,
  "possibleEffects": [
    {
      "baseEffectId": 14,
      "className": "EffectInstanceDice",
      "delay": 0,
      "diceNum": 7,
      "diceSide": 16,
      "dispellable": 1,
      "displayZero": false,
      "duration": 0,
      "effectElement": -1,
      "effectId": 100,
      "effectTriggerDuration": 0,
      "effectUid": 0,
      "forClientOnly": false,
      "group": 0,
      "m_flags": 15,
      "modificator": 0,
      "order": 0,
      "random": 0,
      "spellId": -1,
      "targetId": 0,
      "targetMask": "",
      "trigger": false,
      "triggers": "",
      "value": 0,
      "visibleInBuffUi": true,
      "visibleInFightLog": true,
      "visibleInTooltip": true,
      "visibleOnTerrain": true,
      "zoneDescr": {
        "cellIds": [],
        "damageDecreaseStepPercent": 10,
        "isStopAtTarget": false,
        "maxDamageDecreaseApplyCount": 4,
        "param1": 1,
        "param2": 0,
        "shape": 67
      }
    },
    {
      "baseEffectId": 56,
      "className": "EffectInstanceDice",
      "delay": 0,
      "diceNum": 7,
      "diceSide": 16,
      "dispellable": 1,
      "displayZero": false,
      "duration": 0,
      "effectElement": -1,
      "effectId": 98,
      "effectTriggerDuration": 0,
      "effectUid": 0,
      "forClientOnly": false,
      "group": 0,
      "m_flags": 15,
      "modificator": 0,
      "order": 0,
      "random": 0,
      "spellId": -1,
      "targetId": 0,
      "targetMask": "",
      "trigger": false,
      "triggers": "",
      "value": 0,
      "visibleInBuffUi": true,
      "visibleInFightLog": true,
      "visibleInTooltip": true,
      "visibleOnTerrain": true,
      "zoneDescr": {
        "cellIds": [],
        "damageDecreaseStepPercent": 10,
        "isStopAtTarget": false,
        "maxDamageDecreaseApplyCount": 4,
        "param1": 1,
        "param2": 0,
        "shape": 67
      }
    },
    {
      "baseEffectId": 60,
      "className": "EffectInstanceDice",
      "delay": 0,
      "diceNum": 4,
      "diceSide": 6,
      "dispellable": 1,
      "displayZero": false,
      "duration": 0,
      "effectElement": -1,
      "effectId": 92,
      "effectTriggerDuration": 0,
      "effectUid": 0,
      "forClientOnly": false,
      "group": 0,
      "m_flags": 15,
      "modificator": 0,
      "order": 0,
      "random": 0,
      "spellId": -1,
      "targetId": 0,
      "targetMask": "",
      "trigger": false,
      "triggers": "",
      "value": 0,
      "visibleInBuffUi": true,
      "visibleInFightLog": true,
      "visibleInTooltip": true,
      "visibleOnTerrain": true,
      "zoneDescr": {
        "cellIds": [],
        "damageDecreaseStepPercent": 10,
        "isStopAtTarget": false,
        "maxDamageDecreaseApplyCount": 4,
        "param1": 1,
        "param2": 0,
        "shape": 67
      }
    },
    {
      "baseEffectId": 5,
      "className": "EffectInstanceDice",
      "delay": 0,
      "diceNum": 101,
      "diceSide": 150,
      "dispellable": 1,
      "displayZero": false,
      "duration": 0,
      "effectElement": -1,
      "effectId": 125,
      "effectTriggerDuration": 0,
      "effectUid": 0,
      "forClientOnly": false,
      "group": 0,
      "m_flags": 15,
      "modificator": 0,
      "order": 0,
      "random": 0,
      "spellId": -1,
      "targetId": 0,
      "targetMask": "",
      "trigger": false,
      "triggers": "",
      "value": 0,
      "visibleInBuffUi": true,
      "visibleInFightLog": true,
      "visibleInTooltip": true,
      "visibleOnTerrain": true,
      "zoneDescr": {
        "cellIds": [],
        "damageDecreaseStepPercent": 10,
        "isStopAtTarget": false,
        "maxDamageDecreaseApplyCount": 4,
        "param1": 1,
        "param2": 0,
        "shape": 67
      }
    },
    {
      "baseEffectId": 4,
      "className": "EffectInstanceDice",
      "delay": 0,
      "diceNum": 26,
      "diceSide": 40,
      "dispellable": 1,
      "displayZero": false,
      "duration": 0,
      "effectElement": -1,
      "effectId": 118,
      "effectTriggerDuration": 0,
      "effectUid": 0,
      "forClientOnly": false,
      "group": 0,
      "m_flags": 15,
      "modificator": 0,
      "order": 0,
      "random": 0,
      "spellId": -1,
      "targetId": 0,
      "targetMask": "",
      "trigger": false,
      "triggers": "",
      "value": 0,
      "visibleInBuffUi": true,
      "visibleInFightLog": true,
      "visibleInTooltip": true,
      "visibleOnTerrain": true,
      "zoneDescr": {
        "cellIds": [],
        "damageDecreaseStepPercent": 10,
        "isStopAtTarget": false,
        "maxDamageDecreaseApplyCount": 4,
        "param1": 1,
        "param2": 0,
        "shape": 67
      }
    },
    {
      "baseEffectId": 8,
      "className": "EffectInstanceDice",
      "delay": 0,
      "diceNum": 26,
      "diceSide": 40,
      "dispellable": 1,
      "displayZero": false,
      "duration": 0,
      "effectElement": -1,
      "effectId": 119,
      "effectTriggerDuration": 0,
      "effectUid": 0,
      "forClientOnly": false,
      "group": 0,
      "m_flags": 15,
      "modificator": 0,
      "order": 0,
      "random": 0,
      "spellId": -1,
      "targetId": 0,
      "targetMask": "",
      "trigger": false,
      "triggers": "",
      "value": 0,
      "visibleInBuffUi": true,
      "visibleInFightLog": true,
      "visibleInTooltip": true,
      "visibleOnTerrain": true,
      "zoneDescr": {
        "cellIds": [],
        "damageDecreaseStepPercent": 10,
        "isStopAtTarget": false,
        "maxDamageDecreaseApplyCount": 4,
        "param1": 1,
        "param2": 0,
        "shape": 67
      }
    },
    {
      "baseEffectId": 6,
      "className": "EffectInstanceDice",
      "delay": 0,
      "diceNum": 26,
      "diceSide": 40,
      "dispellable": 1,
      "displayZero": false,
      "duration": 0,
      "effectElement": -1,
      "effectId": 124,
      "effectTriggerDuration": 0,
      "effectUid": 0,
      "forClientOnly": false,
      "group": 0,
      "m_flags": 15,
      "modificator": 0,
      "order": 0,
      "random": 0,
      "spellId": -1,
      "targetId": 0,
      "targetMask": "",
      "trigger": false,
      "triggers": "",
      "value": 0,
      "visibleInBuffUi": true,
      "visibleInFightLog": true,
      "visibleInTooltip": true,
      "visibleOnTerrain": true,
      "zoneDescr": {
        "cellIds": [],
        "damageDecreaseStepPercent": 10,
        "isStopAtTarget": false,
        "maxDamageDecreaseApplyCount": 4,
        "param1": 1,
        "param2": 0,
        "shape": 67
      }
    },
    {
      "baseEffectId": 106,
      "className": "EffectInstanceDice",
      "delay": 0,
      "diceNum": 11,
      "diceSide": 15,
      "dispellable": 1,
      "displayZero": false,
      "duration": 0,
      "effectElement": -1,
      "effectId": 176,
      "effectTriggerDuration": 0,
      "effectUid": 0,
      "forClientOnly": false,
      "group": 0,
      "m_flags": 15,
      "modificator": 0,
      "order": 0,
      "random": 0,
      "spellId": -1,
      "targetId": 0,
      "targetMask": "",
      "trigger": false,
      "triggers": "",
      "value": 0,
      "visibleInBuffUi": true,
      "visibleInFightLog": true,
      "visibleInTooltip": true,
      "visibleOnTerrain": true,
      "zoneDescr": {
        "cellIds": [],
        "damageDecreaseStepPercent": 10,
        "isStopAtTarget": false,
        "maxDamageDecreaseApplyCount": 4,
        "param1": 1,
        "param2": 0,
        "shape": 67
      }
    },
    {
      "baseEffectId": 74,
      "className": "EffectInstanceDice",
      "delay": 0,
      "diceNum": 6,
      "diceSide": 8,
      "dispellable": 1,
      "displayZero": false,
      "duration": 0,
      "effectElement": -1,
      "effectId": 214,
      "effectTriggerDuration": 0,
      "effectUid": 0,
      "forClientOnly": false,
      "group": 0,
      "m_flags": 15,
      "modificator": 0,
      "order": 0,
      "random": 0,
      "spellId": -1,
      "targetId": 0,
      "targetMask": "",
      "trigger": false,
      "triggers": "",
      "value": 0,
      "visibleInBuffUi": true,
      "visibleInFightLog": true,
      "visibleInTooltip": true,
      "visibleOnTerrain": true,
      "zoneDescr": {
        "cellIds": [],
        "damageDecreaseStepPercent": 10,
        "isStopAtTarget": false,
        "maxDamageDecreaseApplyCount": 4,
        "param1": 1,
        "param2": 0,
        "shape": 67
      }
    },
    {
      "baseEffectId": 72,
      "className": "EffectInstanceDice",
      "delay": 0,
      "diceNum": 6,
      "diceSide": 8,
      "dispellable": 1,
      "displayZero": false,
      "duration": 0,
      "effectElement": -1,
      "effectId": 212,
      "effectTriggerDuration": 0,
      "effectUid": 0,
      "forClientOnly": false,
      "group": 0,
      "m_flags": 15,
      "modificator": 0,
      "order": 0,
      "random": 0,
      "spellId": -1,
      "targetId": 0,
      "targetMask": "",
      "trigger": false,
      "triggers": "",
      "value": 0,
      "visibleInBuffUi": true,
      "visibleInFightLog": true,
      "visibleInTooltip": true,
      "visibleOnTerrain": true,
      "zoneDescr": {
        "cellIds": [],
        "damageDecreaseStepPercent": 10,
        "isStopAtTarget": false,
        "maxDamageDecreaseApplyCount": 4,
        "param1": 1,
        "param2": 0,
        "shape": 67
      }
    }
  ],
  "price": 13200,
  "questsThatReward": [],
  "questsThatUse": [],
  "range": 5,
  "realWeight": 10,
  "recipeIds": [],
  "recipeSlots": 8,
  "recipesThatUse": [],
  "recyclingNuggets": 0,
  "resourcesBySubarea": [],
  "secretRecipe": false,
  "slug": {
    "de": "ast des hellen astakrachler",
    "en": "light treeckler branch",
    "es": "rama de abrajidor claro",
    "fr": "branche de l'abrakleur clair",
    "pt": "galho do arvorador claro"
  },
  "startLegendaryTreasureHunt": 0,
  "targetable": false,
  "twoHanded": false,
  "type": {
    "_id": "674e524064788cc741418406",
    "categoryId": 0,
    "className": "ItemTypeData",
    "craftXpRatio": -1,
    "createdAt": "2024-12-03T00:35:12.568Z",
    "evolutiveTypeId": 0,
    "id": 3,
    "isInEncyclopedia": true,
    "m_id": 3,
    "name": {
      "de": "Stab",
      "en": "Wand",
      "es": "Varita",
      "fr": "Baguette",
      "id": "29686",
      "pt": "Varinha"
    },
    "rawZone": "P",
    "superType": {
      "_id": "60abc36ba664687005dfd1bb",
      "className": "ItemSuperTypeData",
      "createdAt": "2021-05-24T15:16:28.560Z",
      "id": 2,
      "m_id": 2,
      "name": {
        "de": "Waffe",
        "en": "Weapon",
        "es": "Arma",
        "fr": "Arme",
        "pt": "Arma"
      },
      "positions": [
        1
      ],
      "updatedAt": "2025-09-23T12:09:10.064Z"
    },
    "superTypeId": 2,
    "updatedAt": "2025-09-23T12:09:10.305Z"
  },
  "typeId": 3,
  "updatedAt": "2025-09-23T12:09:24.445Z",
  "usable": false,
  "visibilityCriterion": ""
}