{
  "_id": "674e524164788cc74141a76c",
  "achievementsThatReward": [],
  "appearanceId": 0,
  "castInDiagonal": false,
  "castInLine": false,
  "castTestLos": false,
  "className": "ItemData",
  "craftConditionalCriterion": "",
  "craftFeasibleCriterion": "SC!5|ST!5",
  "craftVisibleCriterion": "SC!5|ST!5",
  "craftXpRatio": -1,
  "createdAt": "2024-12-03T00:35:12.820Z",
  "criterions": "",
  "criterionsTarget": "",
  "description": {
    "de": "Dieses Amulett \"sieht\" die Zukunft voraus und kann auf jede Aktion entsprechend reagieren. Nur dumm, dass es nicht in der Lage ist zu kommunizieren!",
    "en": "This pendant can look into the future and foresee any event. It really is too bad it doesn't know how to talk.",
    "es": "Este collar ve el futuro y puede anticipar cualquier acción. Una pena que los collares no sepan hablar.",
    "fr": "Ce pendentif voit dans le futur et peut anticiper n'importe quelle action. Il est plutôt regrettable qu'un pendentif ne sache pas communiquer.",
    "id": "481874",
    "pt": "Este pingente prevê o futuro e é capaz de antecipar qualquer ação. É uma pena que os pingentes não possam se comunicar."
  },
  "dropMonsterIds": [],
  "dropSubAreaIds": [],
  "dropTemporisMonsterIds": [],
  "effects": [
    {
      "category": 0,
      "characteristic": 11,
      "effectId": 125,
      "elementId": -1,
      "from": 351,
      "to": 400
    },
    {
      "category": 0,
      "characteristic": 12,
      "effectId": 124,
      "elementId": -1,
      "from": 31,
      "to": 40
    },
    {
      "category": 0,
      "characteristic": 18,
      "effectId": 115,
      "elementId": -1,
      "from": 4,
      "to": 5
    },
    {
      "category": 0,
      "characteristic": 1,
      "effectId": 111,
      "elementId": -1,
      "from": 1,
      "to": 0
    },
    {
      "category": 0,
      "characteristic": 19,
      "effectId": 117,
      "elementId": -1,
      "from": 2,
      "to": 0
    },
    {
      "category": 1,
      "characteristic": 36,
      "effectId": 212,
      "elementId": -1,
      "from": 7,
      "to": 10
    },
    {
      "category": 0,
      "characteristic": 78,
      "effectId": 752,
      "elementId": -1,
      "from": 11,
      "to": 15
    },
    {
      "category": 0,
      "characteristic": 27,
      "effectId": 160,
      "elementId": -1,
      "from": 21,
      "to": 25
    }
  ],
  "enhanceable": true,
  "etheral": false,
  "evolutiveEffectIds": [],
  "exchangeable": true,
  "favoriteRecyclingSubareas": [],
  "favoriteSubAreas": [],
  "favoriteSubAreasBonus": 0,
  "hasLivingObjectSkinJntMood": false,
  "hasRecipe": true,
  "hideEffects": false,
  "iconId": 1263,
  "id": 15746,
  "img": "https://api.dofusdb.fr/img/items/1263.png",
  "importantNotice": {
    "id": "0"
  },
  "isColorable": false,
  "isLegendary": false,
  "isSaleable": true,
  "itemSet": {
    "_id": "674e523f64788cc7414181d0",
    "bonusIsSecret": false,
    "className": "ItemSetData",
    "createdAt": "2024-12-03T00:35:11.399Z",
    "effects": [
      [],
      [
        {
          "category": 0,
          "characteristic": 23,
          "effectId": 128,
          "elementId": -1,
          "from": 1,
          "to": 0
        },
        {
          "category": 0,
          "characteristic": 1,
          "effectId": 111,
          "elementId": -1,
          "from": 1,
          "to": 0
        },
        {
          "category": 0,
          "characteristic": 26,
          "effectId": 182,
          "elementId": -1,
          "from": 1,
          "to": 0
        },
        {
          "category": 0,
          "characteristic": 19,
          "effectId": 117,
          "elementId": -1,
          "from": 1,
          "to": 0
        },
        {
          "category": 0,
          "characteristic": 49,
          "effectId": 178,
          "elementId": -1,
          "from": 35,
          "to": 0
        },
        {
          "category": 0,
          "characteristic": 28,
          "effectId": 161,
          "elementId": -1,
          "from": 35,
          "to": 0
        },
        {
          "category": 0,
          "characteristic": 27,
          "effectId": 160,
          "elementId": -1,
          "from": 35,
          "to": 0
        },
        {
          "category": 0,
          "characteristic": 79,
          "effectId": 753,
          "elementId": -1,
          "from": 20,
          "to": 0
        },
        {
          "category": 0,
          "characteristic": 78,
          "effectId": 752,
          "elementId": -1,
          "from": 25,
          "to": 0
        },
        {
          "category": 0,
          "characteristic": 25,
          "effectId": 138,
          "elementId": 5,
          "from": 80,
          "to": 0
        }
      ],
      [
        {
          "category": 0,
          "characteristic": 26,
          "effectId": 182,
          "elementId": -1,
          "from": 1,
          "to": 0
        },
        {
          "category": 0,
          "characteristic": 19,
          "effectId": 117,
          "elementId": -1,
          "from": 1,
          "to": 0
        },
        {
          "category": 0,
          "characteristic": 49,
          "effectId": 178,
          "elementId": -1,
          "from": 50,
          "to": 0
        },
        {
          "category": 0,
          "characteristic": 28,
          "effectId": 161,
          "elementId": -1,
          "from": 50,
          "to": 0
        },
        {
          "category": 0,
          "characteristic": 27,
          "effectId": 160,
          "elementId": -1,
          "from": 50,
          "to": 0
        },
        {
          "category": 0,
          "characteristic": 79,
          "effectId": 753,
          "elementId": -1,
          "from": 30,
          "to": 0
        },
        {
          "category": 0,
          "characteristic": 78,
          "effectId": 752,
          "elementId": -1,
          "from": 40,
          "to": 0
        },
        {
          "category": 0,
          "characteristic": 23,
          "effectId": 128,
          "elementId": -1,
          "from": 1,
          "to": 0
        },
        {
          "category": 0,
          "characteristic": 1,
          "effectId": 111,
          "elementId": -1,
          "from": 2,
          "to": 0
        },
        {
          "category": 0,
          "characteristic": 25,
          "effectId": 138,
          "elementId": 5,
          "from": 120,
          "to": 0
        }
      ]
    ],
    "id": 357,
    "isCosmetic": false,
    "items": [
      15746,
      15747,
      15748
    ],
    "level": 200,
    "m_id": 357,
    "name": {
      "de": "Harpy-Set",
      "en": "Harpiset",
      "es": "Set de arpilla",
      "fr": "Harpinoplie",
      "id": "469797",
      "pt": "Conjunto Harpilha"
    },
    "possibleEffects": [
      [],
      [
        {
          "baseEffectId": 3,
          "className": "EffectInstanceDice",
          "delay": 0,
          "diceNum": 1,
          "diceSide": 0,
          "dispellable": 1,
          "displayZero": false,
          "duration": 0,
          "effectElement": -1,
          "effectId": 128,
          "effectTriggerDuration": 0,
          "effectUid": 0,
          "forClientOnly": false,
          "group": 0,
          "m_flags": 8,
          "modificator": 0,
          "order": 0,
          "random": 0,
          "spellId": -1,
          "targetId": 0,
          "targetMask": "",
          "trigger": false,
          "triggers": "",
          "value": 0,
          "visibleInBuffUi": false,
          "visibleInFightLog": false,
          "visibleInTooltip": false,
          "visibleOnTerrain": true,
          "zoneDescr": {
            "cellIds": [],
            "damageDecreaseStepPercent": 10,
            "isStopAtTarget": false,
            "maxDamageDecreaseApplyCount": 4,
            "param1": 1,
            "param2": 0,
            "shape": 67
          }
        },
        {
          "baseEffectId": 2,
          "className": "EffectInstanceDice",
          "delay": 0,
          "diceNum": 1,
          "diceSide": 0,
          "dispellable": 1,
          "displayZero": false,
          "duration": 0,
          "effectElement": -1,
          "effectId": 111,
          "effectTriggerDuration": 0,
          "effectUid": 0,
          "forClientOnly": false,
          "group": 0,
          "m_flags": 8,
          "modificator": 0,
          "order": 0,
          "random": 0,
          "spellId": -1,
          "targetId": 0,
          "targetMask": "",
          "trigger": false,
          "triggers": "",
          "value": 0,
          "visibleInBuffUi": false,
          "visibleInFightLog": false,
          "visibleInTooltip": false,
          "visibleOnTerrain": true,
          "zoneDescr": {
            "cellIds": [],
            "damageDecreaseStepPercent": 10,
            "isStopAtTarget": false,
            "maxDamageDecreaseApplyCount": 4,
            "param1": 1,
            "param2": 0,
            "shape": 67
          }
        },
        {
          "baseEffectId": 23,
          "className": "EffectInstanceDice",
          "delay": 0,
          "diceNum": 1,
          "diceSide": 0,
          "dispellable": 1,
          "displayZero": false,
          "duration": 0,
          "effectElement": -1,
          "effectId": 182,
          "effectTriggerDuration": 0,
          "effectUid": 0,
          "forClientOnly": false,
          "group": 0,
          "m_flags": 8,
          "modificator": 0,
          "order": 0,
          "random": 0,
          "spellId": -1,
          "targetId": 0,
          "targetMask": "",
          "trigger": false,
          "triggers": "",
          "value": 0,
          "visibleInBuffUi": false,
          "visibleInFightLog": false,
          "visibleInTooltip": false,
          "visibleOnTerrain": true,
          "zoneDescr": {
            "cellIds": [],
            "damageDecreaseStepPercent": 10,
            "isStopAtTarget": false,
            "maxDamageDecreaseApplyCount": 4,
            "param1": 1,
            "param2": 0,
            "shape": 67
          }
        },
        {
          "baseEffectId": 11,
          "className": "EffectInstanceDice",
          "delay": 0,
          "diceNum": 1,
          "diceSide": 0,
          "dispellable": 1,
          "displayZero": false,
          "duration": 0,
          "effectElement": -1,
          "effectId": 117,
          "effectTriggerDuration": 0,
          "effectUid": 0,
          "forClientOnly": false,
          "group": 0,
          "m_flags": 8,
          "modificator": 0,
          "order": 0,
          "random": 0,
          "spellId": -1,
          "targetId": 0,
          "targetMask": "",
          "trigger": false,
          "triggers": "",
          "value": 0,
          "visibleInBuffUi": false,
          "visibleInFightLog": false,
          "visibleInTooltip": false,
          "visibleOnTerrain": true,
          "zoneDescr": {
            "cellIds": [],
            "damageDecreaseStepPercent": 10,
            "isStopAtTarget": false,
            "maxDamageDecreaseApplyCount": 4,
            "param1": 1,
            "param2": 0,
            "shape": 67
          }
        },
        {
          "baseEffectId": 113,
          "className": "EffectInstanceDice",
          "delay": 0,
          "diceNum": 35,
          "diceSide": 0,
          "dispellable": 1,
          "displayZero": false,
          "duration": 0,
          "effectElement": -1,
          "effectId": 178,
          "effectTriggerDuration": 0,
          "effectUid": 0,
          "forClientOnly": false,
          "group": 0,
          "m_flags": 8,
          "modificator": 0,
          "order": 0,
          "random": 0,
          "spellId": -1,
          "targetId": 0,
          "targetMask": "",
          "trigger": false,
          "triggers": "",
          "value": 0,
          "visibleInBuffUi": false,
          "visibleInFightLog": false,
          "visibleInTooltip": false,
          "visibleOnTerrain": true,
          "zoneDescr": {
            "cellIds": [],
            "damageDecreaseStepPercent": 10,
            "isStopAtTarget": false,
            "maxDamageDecreaseApplyCount": 4,
            "param1": 1,
            "param2": 0,
            "shape": 67
          }
        },
        {
          "baseEffectId": 351,
          "className": "EffectInstanceDice",
          "delay": 0,
          "diceNum": 35,
          "diceSide": 0,
          "dispellable": 1,
          "displayZero": false,
          "duration": 0,
          "effectElement": -1,
          "effectId": 161,
          "effectTriggerDuration": 0,
          "effectUid": 0,
          "forClientOnly": false,
          "group": 0,
          "m_flags": 8,
          "modificator": 0,
          "order": 0,
          "random": 0,
          "spellId": -1,
          "targetId": 0,
          "targetMask": "",
          "trigger": false,
          "triggers": "",
          "value": 0,
          "visibleInBuffUi": false,
          "visibleInFightLog": false,
          "visibleInTooltip": false,
          "visibleOnTerrain": true,
          "zoneDescr": {
            "cellIds": [],
            "damageDecreaseStepPercent": 10,
            "isStopAtTarget": false,
            "maxDamageDecreaseApplyCount": 4,
            "param1": 1,
            "param2": 0,
            "shape": 67
          }
        },
        {
          "baseEffectId": 349,
          "className": "EffectInstanceDice",
          "delay": 0,
          "diceNum": 35,
          "diceSide": 0,
          "dispellable": 1,
          "displayZero": false,
          "duration": 0,
          "effectElement": -1,
          "effectId": 160,
          "effectTriggerDuration": 0,
          "effectUid": 0,
          "forClientOnly": false,
          "group": 0,
          "m_flags": 8,
          "modificator": 0,
          "order": 0,
          "random": 0,
          "spellId": -1,
          "targetId": 0,
          "targetMask": "",
          "trigger": false,
          "triggers": "",
          "value": 0,
          "visibleInBuffUi": false,
          "visibleInFightLog": false,
          "visibleInTooltip": false,
          "visibleOnTerrain": true,
          "zoneDescr": {
            "cellIds": [],
            "damageDecreaseStepPercent": 10,
            "isStopAtTarget": false,
            "maxDamageDecreaseApplyCount": 4,
            "param1": 1,
            "param2": 0,
            "shape": 67
          }
        },
        {
          "baseEffectId": 344,
          "className": "EffectInstanceDice",
          "delay": 0,
          "diceNum": 20,
          "diceSide": 0,
          "dispellable": 1,
          "displayZero": false,
          "duration": 0,
          "effectElement": -1,
          "effectId": 753,
          "effectTriggerDuration": 0,
          "effectUid": 0,
          "forClientOnly": false,
          "group": 0,
          "m_flags": 8,
          "modificator": 0,
          "order": 0,
          "random": 0,
          "spellId": -1,
          "targetId": 0,
          "targetMask": "",
          "trigger": false,
          "triggers": "",
          "value": 0,
          "visibleInBuffUi": false,
          "visibleInFightLog": false,
          "visibleInTooltip": false,
          "visibleOnTerrain": true,
          "zoneDescr": {
            "cellIds": [],
            "damageDecreaseStepPercent": 10,
            "isStopAtTarget": false,
            "maxDamageDecreaseApplyCount": 4,
            "param1": 1,
            "param2": 0,
            "shape": 67
          }
        },
        {
          "baseEffectId": 343,
          "className": "EffectInstanceDice",
          "delay": 0,
          "diceNum": 25,
          "diceSide": 0,
          "dispellable": 1,
          "displayZero": false,
          "duration": 0,
          "effectElement": -1,
          "effectId": 752,
          "effectTriggerDuration": 0,
          "effectUid": 0,
          "forClientOnly": false,
          "group": 0,
          "m_flags": 8,
          "modificator": 0,
          "order": 0,
          "random": 0,
          "spellId": -1,
          "targetId": 0,
          "targetMask": "",
          "trigger": false,
          "triggers": "",
          "value": 0,
          "visibleInBuffUi": false,
          "visibleInFightLog": false,
          "visibleInTooltip": false,
          "visibleOnTerrain": true,
          "zoneDescr": {
            "cellIds": [],
            "damageDecreaseStepPercent": 10,
            "isStopAtTarget": false,
            "maxDamageDecreaseApplyCount": 4,
            "param1": 1,
            "param2": 0,
            "shape": 67
          }
        },
        {
          "baseEffectId": 22,
          "className": "EffectInstanceDice",
          "delay": 0,
          "diceNum": 80,
          "diceSide": 0,
          "dispellable": 1,
          "displayZero": false,
          "duration": 0,
          "effectElement": -1,
          "effectId": 138,
          "effectTriggerDuration": 0,
          "effectUid": 0,
          "forClientOnly": false,
          "group": 0,
          "m_flags": 8,
          "modificator": 0,
          "order": 0,
          "random": 0,
          "spellId": -1,
          "targetId": 0,
          "targetMask": "",
          "trigger": false,
          "triggers": "",
          "value": 0,
          "visibleInBuffUi": false,
          "visibleInFightLog": false,
          "visibleInTooltip": false,
          "visibleOnTerrain": true,
          "zoneDescr": {
            "cellIds": [],
            "damageDecreaseStepPercent": 10,
            "isStopAtTarget": false,
            "maxDamageDecreaseApplyCount": 4,
            "param1": 1,
            "param2": 0,
            "shape": 67
          }
        }
      ],
      [
        {
          "baseEffectId": 23,
          "className": "EffectInstanceDice",
          "delay": 0,
          "diceNum": 1,
          "diceSide": 0,
          "dispellable": 1,
          "displayZero": false,
          "duration": 0,
          "effectElement": -1,
          "effectId": 182,
          "effectTriggerDuration": 0,
          "effectUid": 0,
          "forClientOnly": false,
          "group": 0,
          "m_flags": 8,
          "modificator": 0,
          "order": 0,
          "random": 0,
          "spellId": -1,
          "targetId": 0,
          "targetMask": "",
          "trigger": false,
          "triggers": "",
          "value": 0,
          "visibleInBuffUi": false,
          "visibleInFightLog": false,
          "visibleInTooltip": false,
          "visibleOnTerrain": true,
          "zoneDescr": {
            "cellIds": [],
            "damageDecreaseStepPercent": 10,
            "isStopAtTarget": false,
            "maxDamageDecreaseApplyCount": 4,
            "param1": 1,
            "param2": 0,
            "shape": 67
          }
        },
        {
          "baseEffectId": 11,
          "className": "EffectInstanceDice",
          "delay": 0,
          "diceNum": 1,
          "diceSide": 0,
          "dispellable": 1,
          "displayZero": false,
          "duration": 0,
          "effectElement": -1,
          "effectId": 117,
          "effectTriggerDuration": 0,
          "effectUid": 0,
          "forClientOnly": false,
          "group": 0,
          "m_flags": 8,
          "modificator": 0,
          "order": 0,
          "random": 0,
          "spellId": -1,
          "targetId": 0,
          "targetMask": "",
          "trigger": false,
          "triggers": "",
          "value": 0,
          "visibleInBuffUi": false,
          "visibleInFightLog": false,
          "visibleInTooltip": false,
          "visibleOnTerrain": true,
          "zoneDescr": {
            "cellIds": [],
            "damageDecreaseStepPercent": 10,
            "isStopAtTarget": false,
            "maxDamageDecreaseApplyCount": 4,
            "param1": 1,
            "param2": 0,
            "shape": 67
          }
        },
        {
          "baseEffectId": 113,
          "className": "EffectInstanceDice",
          "delay": 0,
          "diceNum": 50,
          "diceSide": 0,
          "dispellable": 1,
          "displayZero": false,
          "duration": 0,
          "effectElement": -1,
          "effectId": 178,
          "effectTriggerDuration": 0,
          "effectUid": 0,
          "forClientOnly": false,
          "group": 0,
          "m_flags": 8,
          "modificator": 0,
          "order": 0,
          "random": 0,
          "spellId": -1,
          "targetId": 0,
          "targetMask": "",
          "trigger": false,
          "triggers": "",
          "value": 0,
          "visibleInBuffUi": false,
          "visibleInFightLog": false,
          "visibleInTooltip": false,
          "visibleOnTerrain": true,
          "zoneDescr": {
            "cellIds": [],
            "damageDecreaseStepPercent": 10,
            "isStopAtTarget": false,
            "maxDamageDecreaseApplyCount": 4,
            "param1": 1,
            "param2": 0,
            "shape": 67
          }
        },
        {
          "baseEffectId": 351,
          "className": "EffectInstanceDice",
          "delay": 0,
          "diceNum": 50,
          "diceSide": 0,
          "dispellable": 1,
          "displayZero": false,
          "duration": 0,
          "effectElement": -1,
          "effectId": 161,
          "effectTriggerDuration": 0,
          "effectUid": 0,
          "forClientOnly": false,
          "group": 0,
          "m_flags": 8,
          "modificator": 0,
          "order": 0,
          "random": 0,
          "spellId": -1,
          "targetId": 0,
          "targetMask": "",
          "trigger": false,
          "triggers": "",
          "value": 0,
          "visibleInBuffUi": false,
          "visibleInFightLog": false,
          "visibleInTooltip": false,
          "visibleOnTerrain": true,
          "zoneDescr": {
            "cellIds": [],
            "damageDecreaseStepPercent": 10,
            "isStopAtTarget": false,
            "maxDamageDecreaseApplyCount": 4,
            "param1": 1,
            "param2": 0,
            "shape": 67
          }
        },
        {
          "baseEffectId": 349,
          "className": "EffectInstanceDice",
          "delay": 0,
          "diceNum": 50,
          "diceSide": 0,
          "dispellable": 1,
          "displayZero": false,
          "duration": 0,
          "effectElement": -1,
          "effectId": 160,
          "effectTriggerDuration": 0,
          "effectUid": 0,
          "forClientOnly": false,
          "group": 0,
          "m_flags": 8,
          "modificator": 0,
          "order": 0,
          "random": 0,
          "spellId": -1,
          "targetId": 0,
          "targetMask": "",
          "trigger": false,
          "triggers": "",
          "value": 0,
          "visibleInBuffUi": false,
          "visibleInFightLog": false,
          "visibleInTooltip": false,
          "visibleOnTerrain": true,
          "zoneDescr": {
            "cellIds": [],
            "damageDecreaseStepPercent": 10,
            "isStopAtTarget": false,
            "maxDamageDecreaseApplyCount": 4,
            "param1": 1,
            "param2": 0,
            "shape": 67
          }
        },
        {
          "baseEffectId": 344,
          "className": "EffectInstanceDice",
          "delay": 0,
          "diceNum": 30,
          "diceSide": 0,
          "dispellable": 1,
          "displayZero": false,
          "duration": 0,
          "effectElement": -1,
          "effectId": 753,
          "effectTriggerDuration": 0,
          "effectUid": 0,
          "forClientOnly": false,
          "group": 0,
          "m_flags": 8,
          "modificator": 0,
          "order": 0,
          "random": 0,
          "spellId": -1,
          "targetId": 0,
          "targetMask": "",
          "trigger": false,
          "triggers": "",
          "value": 0,
          "visibleInBuffUi": false,
          "visibleInFightLog": false,
          "visibleInTooltip": false,
          "visibleOnTerrain": true,
          "zoneDescr": {
            "cellIds": [],
            "damageDecreaseStepPercent": 10,
            "isStopAtTarget": false,
            "maxDamageDecreaseApplyCount": 4,
            "param1": 1,
            "param2": 0,
            "shape": 67
          }
        },
        {
          "baseEffectId": 343,
          "className": "EffectInstanceDice",
          "delay": 0,
          "diceNum": 40,
          "diceSide": 0,
          "dispellable": 1,
          "displayZero": false,
          "duration": 0,
          "effectElement": -1,
          "effectId": 752,
          "effectTriggerDuration": 0,
          "effectUid": 0,
          "forClientOnly": false,
          "group": 0,
          "m_flags": 8,
          "modificator": 0,
          "order": 0,
          "random": 0,
          "spellId": -1,
          "targetId": 0,
          "targetMask": "",
          "trigger": false,
          "triggers": "",
          "value": 0,
          "visibleInBuffUi": false,
          "visibleInFightLog": false,
          "visibleInTooltip": false,
          "visibleOnTerrain": true,
          "zoneDescr": {
            "cellIds": [],
            "damageDecreaseStepPercent": 10,
            "isStopAtTarget": false,
            "maxDamageDecreaseApplyCount": 4,
            "param1": 1,
            "param2": 0,
            "shape": 67
          }
        },
        {
          "baseEffectId": 3,
          "className": "EffectInstanceDice",
          "delay": 0,
          "diceNum": 1,
          "diceSide": 0,
          "dispellable": 1,
          "displayZero": false,
          "duration": 0,
          "effectElement": -1,
          "effectId": 128,
          "effectTriggerDuration": 0,
          "effectUid": 0,
          "forClientOnly": false,
          "group": 0,
          "m_flags": 8,
          "modificator": 0,
          "order": 0,
          "random": 0,
          "spellId": -1,
          "targetId": 0,
          "targetMask": "",
          "trigger": false,
          "triggers": "",
          "value": 0,
          "visibleInBuffUi": false,
          "visibleInFightLog": false,
          "visibleInTooltip": false,
          "visibleOnTerrain": true,
          "zoneDescr": {
            "cellIds": [],
            "damageDecreaseStepPercent": 10,
            "isStopAtTarget": false,
            "maxDamageDecreaseApplyCount": 4,
            "param1": 1,
            "param2": 0,
            "shape": 67
          }
        },
        {
          "baseEffectId": 2,
          "className": "EffectInstanceDice",
          "delay": 0,
          "diceNum": 2,
          "diceSide": 0,
          "dispellable": 1,
          "displayZero": false,
          "duration": 0,
          "effectElement": -1,
          "effectId": 111,
          "effectTriggerDuration": 0,
          "effectUid": 0,
          "forClientOnly": false,
          "group": 0,
          "m_flags": 8,
          "modificator": 0,
          "order": 0,
          "random": 0,
          "spellId": -1,
          "targetId": 0,
          "targetMask": "",
          "trigger": false,
          "triggers": "",
          "value": 0,
          "visibleInBuffUi": false,
          "visibleInFightLog": false,
          "visibleInTooltip": false,
          "visibleOnTerrain": true,
          "zoneDescr": {
            "cellIds": [],
            "damageDecreaseStepPercent": 10,
            "isStopAtTarget": false,
            "maxDamageDecreaseApplyCount": 4,
            "param1": 1,
            "param2": 0,
            "shape": 67
          }
        },
        {
          "baseEffectId": 22,
          "className": "EffectInstanceDice",
          "delay": 0,
          "diceNum": 120,
          "diceSide": 0,
          "dispellable": 1,
          "displayZero": false,
          "duration": 0,
          "effectElement": -1,
          "effectId": 138,
          "effectTriggerDuration": 0,
          "effectUid": 0,
          "forClientOnly": false,
          "group": 0,
          "m_flags": 8,
          "modificator": 0,
          "order": 0,
          "random": 0,
          "spellId": -1,
          "targetId": 0,
          "targetMask": "",
          "trigger": false,
          "triggers": "",
          "value": 0,
          "visibleInBuffUi": false,
          "visibleInFightLog": false,
          "visibleInTooltip": false,
          "visibleOnTerrain": true,
          "zoneDescr": {
            "cellIds": [],
            "damageDecreaseStepPercent": 10,
            "isStopAtTarget": false,
            "maxDamageDecreaseApplyCount": 4,
            "param1": 1,
            "param2": 0,
            "shape": 67
          }
        }
      ]
    ],
    "slug": {
      "de": "harpy-set",
      "en": "harpiset",
      "es": "set de arpilla",
      "fr": "harpinoplie",
      "pt": "conjunto harpilha"
    },
    "typeIds": [
      1,
      17,
      11
    ],
    "updatedAt": "2025-09-23T12:09:09.389Z"
  },
  "itemSetId": 357,
  "legendaryTreasureHuntThatReward": 0,
  "level": 200,
  "m_flags": 1092,
  "m_id": 15746,
  "name": {
    "de": "Harpy-Amulett",
    "en": "Neckross",
    "es": "Collarpilla",
    "fr": "Harpendentif",
    "id": "481873",
    "pt": "Harpingente"
  },
  "needUseConfirm": false,
  "nonUsableOnAnother": false,
  "possibleEffects": [
    {
      "baseEffectId": 5,
      "className": "EffectInstanceDice",
      "delay": 0,
      "diceNum": 351,
      "diceSide": 400,
      "dispellable": 1,
      "displayZero": false,
      "duration": 0,
      "effectElement": -1,
      "effectId": 125,
      "effectTriggerDuration": 0,
      "effectUid": 0,
      "forClientOnly": false,
      "group": 0,
      "m_flags": 15,
      "modificator": 0,
      "order": 0,
      "random": 0,
      "spellId": -1,
      "targetId": 0,
      "targetMask": "",
      "trigger": false,
      "triggers": "",
      "value": 0,
      "visibleInBuffUi": true,
      "visibleInFightLog": true,
      "visibleInTooltip": true,
      "visibleOnTerrain": true,
      "zoneDescr": {
        "cellIds": [],
        "damageDecreaseStepPercent": 10,
        "isStopAtTarget": false,
        "maxDamageDecreaseApplyCount": 4,
        "param1": 1,
        "param2": 0,
        "shape": 67
      }
    },
    {
      "baseEffectId": 6,
      "className": "EffectInstanceDice",
      "delay": 0,
      "diceNum": 31,
      "diceSide": 40,
      "dispellable": 1,
      "displayZero": false,
      "duration": 0,
      "effectElement": -1,
      "effectId": 124,
      "effectTriggerDuration": 0,
      "effectUid": 0,
      "forClientOnly": false,
      "group": 0,
      "m_flags": 15,
      "modificator": 0,
      "order": 0,
      "random": 0,
      "spellId": -1,
      "targetId": 0,
      "targetMask": "",
      "trigger": false,
      "triggers": "",
      "value": 0,
      "visibleInBuffUi": true,
      "visibleInFightLog": true,
      "visibleInTooltip": true,
      "visibleOnTerrain": true,
      "zoneDescr": {
        "cellIds": [],
        "damageDecreaseStepPercent": 10,
        "isStopAtTarget": false,
        "maxDamageDecreaseApplyCount": 4,
        "param1": 1,
        "param2": 0,
        "shape": 67
      }
    },
    {
      "baseEffectId": 10,
      "className": "EffectInstanceDice",
      "delay": 0,
      "diceNum": 4,
      "diceSide": 5,
      "dispellable": 1,
      "displayZero": false,
      "duration": 0,
      "effectElement": -1,
      "effectId": 115,
      "effectTriggerDuration": 0,
      "effectUid": 0,
      "forClientOnly": false,
      "group": 0,
      "m_flags": 15,
      "modificator": 0,
      "order": 0,
      "random": 0,
      "spellId": -1,
      "targetId": 0,
      "targetMask": "",
      "trigger": false,
      "triggers": "",
      "value": 0,
      "visibleInBuffUi": true,
      "visibleInFightLog": true,
      "visibleInTooltip": true,
      "visibleOnTerrain": true,
      "zoneDescr": {
        "cellIds": [],
        "damageDecreaseStepPercent": 10,
        "isStopAtTarget": false,
        "maxDamageDecreaseApplyCount": 4,
        "param1": 1,
        "param2": 0,
        "shape": 67
      }
    },
    {
      "baseEffectId": 2,
      "className": "EffectInstanceDice",
      "delay": 0,
      "diceNum": 1,
      "diceSide": 0,
      "dispellable": 1,
      "displayZero": false,
      "duration": 0,
      "effectElement": -1,
      "effectId": 111,
      "effectTriggerDuration": 0,
      "effectUid": 0,
      "forClientOnly": false,
      "group": 0,
      "m_flags": 15,
      "modificator": 0,
      "order": 0,
      "random": 0,
      "spellId": -1,
      "targetId": 0,
      "targetMask": "",
      "trigger": false,
      "triggers": "",
      "value": 0,
      "visibleInBuffUi": true,
      "visibleInFightLog": true,
      "visibleInTooltip": true,
      "visibleOnTerrain": true,
      "zoneDescr": {
        "cellIds": [],
        "damageDecreaseStepPercent": 10,
        "isStopAtTarget": false,
        "maxDamageDecreaseApplyCount": 4,
        "param1": 1,
        "param2": 0,
        "shape": 67
      }
    },
    {
      "baseEffectId": 11,
      "className": "EffectInstanceDice",
      "delay": 0,
      "diceNum": 2,
      "diceSide": 0,
      "dispellable": 1,
      "displayZero": false,
      "duration": 0,
      "effectElement": -1,
      "effectId": 117,
      "effectTriggerDuration": 0,
      "effectUid": 0,
      "forClientOnly": false,
      "group": 0,
      "m_flags": 15,
      "modificator": 0,
      "order": 0,
      "random": 0,
      "spellId": -1,
      "targetId": 0,
      "targetMask": "",
      "trigger": false,
      "triggers": "",
      "value": 0,
      "visibleInBuffUi": true,
      "visibleInFightLog": true,
      "visibleInTooltip": true,
      "visibleOnTerrain": true,
      "zoneDescr": {
        "cellIds": [],
        "damageDecreaseStepPercent": 10,
        "isStopAtTarget": false,
        "maxDamageDecreaseApplyCount": 4,
        "param1": 1,
        "param2": 0,
        "shape": 67
      }
    },
    {
      "baseEffectId": 72,
      "className": "EffectInstanceDice",
      "delay": 0,
      "diceNum": 7,
      "diceSide": 10,
      "dispellable": 1,
      "displayZero": false,
      "duration": 0,
      "effectElement": -1,
      "effectId": 212,
      "effectTriggerDuration": 0,
      "effectUid": 0,
      "forClientOnly": false,
      "group": 0,
      "m_flags": 15,
      "modificator": 0,
      "order": 0,
      "random": 0,
      "spellId": -1,
      "targetId": 0,
      "targetMask": "",
      "trigger": false,
      "triggers": "",
      "value": 0,
      "visibleInBuffUi": true,
      "visibleInFightLog": true,
      "visibleInTooltip": true,
      "visibleOnTerrain": true,
      "zoneDescr": {
        "cellIds": [],
        "damageDecreaseStepPercent": 10,
        "isStopAtTarget": false,
        "maxDamageDecreaseApplyCount": 4,
        "param1": 1,
        "param2": 0,
        "shape": 67
      }
    },
    {
      "baseEffectId": 343,
      "className": "EffectInstanceDice",
      "delay": 0,
      "diceNum": 11,
      "diceSide": 15,
      "dispellable": 1,
      "displayZero": false,
      "duration": 0,
      "effectElement": -1,
      "effectId": 752,
      "effectTriggerDuration": 0,
      "effectUid": 0,
      "forClientOnly": false,
      "group": 0,
      "m_flags": 15,
      "modificator": 0,
      "order": 0,
      "random": 0,
      "spellId": -1,
      "targetId": 0,
      "targetMask": "",
      "trigger": false,
      "triggers": "",
      "value": 0,
      "visibleInBuffUi": true,
      "visibleInFightLog": true,
      "visibleInTooltip": true,
      "visibleOnTerrain": true,
      "zoneDescr": {
        "cellIds": [],
        "damageDecreaseStepPercent": 10,
        "isStopAtTarget": false,
        "maxDamageDecreaseApplyCount": 4,
        "param1": 1,
        "param2": 0,
        "shape": 67
      }
    },
    {
      "baseEffectId": 349,
      "className": "EffectInstanceDice",
      "delay": 0,
      "diceNum": 21,
      "diceSide": 25,
      "dispellable": 1,
      "displayZero": false,
      "duration": 0,
      "effectElement": -1,
      "effectId": 160,
      "effectTriggerDuration": 0,
      "effectUid": 0,
      "forClientOnly": false,
      "group": 0,
      "m_flags": 15,
      "modificator": 0,
      "order": 0,
      "random": 0,
      "spellId": -1,
      "targetId": 0,
      "targetMask": "",
      "trigger": false,
      "triggers": "",
      "value": 0,
      "visibleInBuffUi": true,
      "visibleInFightLog": true,
      "visibleInTooltip": true,
      "visibleOnTerrain": true,
      "zoneDescr": {
        "cellIds": [],
        "damageDecreaseStepPercent": 10,
        "isStopAtTarget": false,
        "maxDamageDecreaseApplyCount": 4,
        "param1": 1,
        "param2": 0,
        "shape": 67
      }
    }
  ],
  "price": 20000,
  "questsThatReward": [],
  "questsThatUse": [],
  "realWeight": 10,
  "recipeIds": [],
  "recipeSlots": 8,
  "recipesThatUse": [],
  "recyclingNuggets": 0,
  "resourcesBySubarea": [],
  "secretRecipe": false,
  "slug": {
    "de": "harpy-amulett",
    "en": "neckross",
    "es": "collarpilla",
    "fr": "harpendentif",
    "pt": "harpingente"
  },
  "startLegendaryTreasureHunt": 0,
  "targetable": false,
  "twoHanded": false,
  "type": {
    "_id": "674e524064788cc741418404",
    "categoryId": 0,
    "className": "ItemTypeData",
    "craftXpRatio": -1,
    "createdAt": "2024-12-03T00:35:12.568Z",
    "evolutiveTypeId": 0,
    "id": 1,
    "isInEncyclopedia": true,
    "m_id": 1,
    "name": {
      "de": "Amulett",
      "en": "Amulet",
      "es": "Amuleto",
      "fr": "Amulette",
      "id": "915868",
      "pt": "Amuleto"
    },
    "rawZone": "",
    "superType": {
      "_id": "60abc34ca664687005dfd1b9",
      "className": "ItemSuperTypeData",
      "createdAt": "2021-05-24T15:16:28.560Z",
      "id": 1,
      "m_id": 1,
      "name": {
        "de": "Amulett",
        "en": "Amulet",
        "es": "Amuleto",
        "fr": "Amulette",
        "pt": "Amuleto"
      },
      "positions": [
        0
      ],
      "updatedAt": "2025-09-23T12:09:10.064Z"
    },
    "superTypeId": 1,
    "updatedAt": "2025-09-23T12:09:10.305Z"
  },
  "typeId": 1,
  "updatedAt": "2025-09-23T12:09:26.347Z",
  "usable": false,
  "visibilityCriterion": ""
}