{
  "_id": "674e524064788cc741419e6e",
  "achievementsThatReward": [],
  "appearanceId": 0,
  "castInDiagonal": false,
  "castInLine": false,
  "castTestLos": false,
  "className": "ItemData",
  "craftConditionalCriterion": "",
  "craftFeasibleCriterion": "SC!5|ST!5",
  "craftVisibleCriterion": "SC!5|ST!5",
  "craftXpRatio": -1,
  "createdAt": "2024-12-03T00:35:12.820Z",
  "criterions": "",
  "criterionsTarget": "",
  "description": {
    "de": "Dieses Schuhe bieten die höchste Sicherheit in der ganzen Welt der Zwölf. Mit den Dingern an den Füßen wird es niemandem gelingen, eure Strümpfe von den Füßen zu stehlen... (Wer auch immer selbstmörderisch genug sein sollte, so etwas verrücktes zu tun).",
    "en": "These boots are the safest boots in the World of Twelve. Pop them on your feet and you can be sure that nobody will steal your socks. Please note: toe-stubbing protection not included.",
    "es": "Estas botas son las más seguras de todo el Mundo de los Doce. Con ellas en los pies, puedes estar seguro que nadie vendrá a robarte tus calcetines. No obstante, no protegerá tus deditos de los pies de los golpes contra las mesas, las sillas y demás muebles asesinos.",
    "fr": "Ces bottes sont les plus sûres de tout le Monde des Douze. Avec ça aux pieds, vous êtes assurés que plus personne ne viendra voler vos chaussettes. Ne protège pas vos petits orteils des coups de tables basses, chaises et autres ameublements meurtriers.",
    "id": "98030",
    "pt": "Estas botas são as mais seguras do Mundo dos Doze. Com isso nos pés, você vai ter certeza de que ninguém mais virá roubar seus sapatos. Não protege seus dedinhos de pancadas de mesas baixas, de cadeiras e de outros móveis assassinos."
  },
  "dropMonsterIds": [],
  "dropSubAreaIds": [],
  "dropTemporisMonsterIds": [],
  "effects": [
    {
      "category": 0,
      "characteristic": 11,
      "effectId": 125,
      "elementId": -1,
      "from": 16,
      "to": 20
    },
    {
      "category": 0,
      "characteristic": 18,
      "effectId": 115,
      "elementId": -1,
      "from": 2,
      "to": 0
    },
    {
      "category": 0,
      "characteristic": 23,
      "effectId": 128,
      "elementId": -1,
      "from": 1,
      "to": 0
    },
    {
      "category": 0,
      "characteristic": 91,
      "effectId": 428,
      "elementId": 4,
      "from": 2,
      "to": 3
    },
    {
      "category": 0,
      "characteristic": 28,
      "effectId": 161,
      "elementId": -1,
      "from": 2,
      "to": 3
    },
    {
      "category": 0,
      "characteristic": 87,
      "effectId": 421,
      "elementId": -1,
      "from": -10,
      "to": 0
    },
    {
      "category": 0,
      "characteristic": 85,
      "effectId": 417,
      "elementId": -1,
      "from": -10,
      "to": 0
    }
  ],
  "enhanceable": true,
  "etheral": false,
  "evolutiveEffectIds": [],
  "exchangeable": true,
  "favoriteRecyclingSubareas": [],
  "favoriteSubAreas": [],
  "favoriteSubAreasBonus": 0,
  "hasLivingObjectSkinJntMood": false,
  "hasRecipe": true,
  "hideEffects": false,
  "iconId": 11218,
  "id": 13139,
  "img": "https://api.dofusdb.fr/img/items/11218.png",
  "importantNotice": {
    "id": "0"
  },
  "isColorable": false,
  "isLegendary": false,
  "isSaleable": true,
  "itemSet": {
    "_id": "674e523f64788cc741418182",
    "bonusIsSecret": false,
    "className": "ItemSetData",
    "createdAt": "2024-12-03T00:35:11.399Z",
    "effects": [
      [],
      [
        {
          "category": 0,
          "characteristic": 11,
          "effectId": 125,
          "elementId": -1,
          "from": 10,
          "to": 0
        },
        {
          "category": 0,
          "characteristic": 12,
          "effectId": 124,
          "elementId": -1,
          "from": 10,
          "to": 0
        },
        {
          "category": 0,
          "characteristic": 25,
          "effectId": 138,
          "elementId": 5,
          "from": 10,
          "to": 0
        }
      ],
      [
        {
          "category": 0,
          "characteristic": 11,
          "effectId": 125,
          "elementId": -1,
          "from": 20,
          "to": 0
        },
        {
          "category": 0,
          "characteristic": 12,
          "effectId": 124,
          "elementId": -1,
          "from": 20,
          "to": 0
        },
        {
          "category": 0,
          "characteristic": 25,
          "effectId": 138,
          "elementId": 5,
          "from": 20,
          "to": 0
        },
        {
          "category": 0,
          "characteristic": 19,
          "effectId": 117,
          "elementId": -1,
          "from": 1,
          "to": 0
        }
      ],
      [
        {
          "category": 0,
          "characteristic": 11,
          "effectId": 125,
          "elementId": -1,
          "from": 40,
          "to": 0
        },
        {
          "category": 0,
          "characteristic": 12,
          "effectId": 124,
          "elementId": -1,
          "from": 40,
          "to": 0
        },
        {
          "category": 0,
          "characteristic": 25,
          "effectId": 138,
          "elementId": 5,
          "from": 40,
          "to": 0
        },
        {
          "category": 0,
          "characteristic": 19,
          "effectId": 117,
          "elementId": -1,
          "from": 2,
          "to": 0
        },
        {
          "category": 0,
          "characteristic": 1,
          "effectId": 111,
          "elementId": -1,
          "from": 1,
          "to": 0
        }
      ]
    ],
    "id": 246,
    "isCosmetic": false,
    "items": [
      13136,
      13137,
      13138,
      13139
    ],
    "level": 56,
    "m_id": 246,
    "name": {
      "de": "Truhen-Set",
      "en": "Chest Set",
      "es": "Set cofre",
      "fr": "Panoplie Coffre",
      "id": "94694",
      "pt": "Conjunto Baú"
    },
    "possibleEffects": [
      [],
      [
        {
          "baseEffectId": 5,
          "className": "EffectInstanceDice",
          "delay": 0,
          "diceNum": 10,
          "diceSide": 0,
          "dispellable": 1,
          "displayZero": false,
          "duration": 0,
          "effectElement": -1,
          "effectId": 125,
          "effectTriggerDuration": 0,
          "effectUid": 0,
          "forClientOnly": false,
          "group": 0,
          "m_flags": 8,
          "modificator": 0,
          "order": 0,
          "random": 0,
          "spellId": -1,
          "targetId": 0,
          "targetMask": "",
          "trigger": false,
          "triggers": "",
          "value": 0,
          "visibleInBuffUi": false,
          "visibleInFightLog": false,
          "visibleInTooltip": false,
          "visibleOnTerrain": true,
          "zoneDescr": {
            "cellIds": [],
            "damageDecreaseStepPercent": 10,
            "isStopAtTarget": false,
            "maxDamageDecreaseApplyCount": 4,
            "param1": 1,
            "param2": 0,
            "shape": 67
          }
        },
        {
          "baseEffectId": 6,
          "className": "EffectInstanceDice",
          "delay": 0,
          "diceNum": 10,
          "diceSide": 0,
          "dispellable": 1,
          "displayZero": false,
          "duration": 0,
          "effectElement": -1,
          "effectId": 124,
          "effectTriggerDuration": 0,
          "effectUid": 0,
          "forClientOnly": false,
          "group": 0,
          "m_flags": 8,
          "modificator": 0,
          "order": 0,
          "random": 0,
          "spellId": -1,
          "targetId": 0,
          "targetMask": "",
          "trigger": false,
          "triggers": "",
          "value": 0,
          "visibleInBuffUi": false,
          "visibleInFightLog": false,
          "visibleInTooltip": false,
          "visibleOnTerrain": true,
          "zoneDescr": {
            "cellIds": [],
            "damageDecreaseStepPercent": 10,
            "isStopAtTarget": false,
            "maxDamageDecreaseApplyCount": 4,
            "param1": 1,
            "param2": 0,
            "shape": 67
          }
        },
        {
          "baseEffectId": 22,
          "className": "EffectInstanceDice",
          "delay": 0,
          "diceNum": 10,
          "diceSide": 0,
          "dispellable": 1,
          "displayZero": false,
          "duration": 0,
          "effectElement": -1,
          "effectId": 138,
          "effectTriggerDuration": 0,
          "effectUid": 0,
          "forClientOnly": false,
          "group": 0,
          "m_flags": 8,
          "modificator": 0,
          "order": 0,
          "random": 0,
          "spellId": -1,
          "targetId": 0,
          "targetMask": "",
          "trigger": false,
          "triggers": "",
          "value": 0,
          "visibleInBuffUi": false,
          "visibleInFightLog": false,
          "visibleInTooltip": false,
          "visibleOnTerrain": true,
          "zoneDescr": {
            "cellIds": [],
            "damageDecreaseStepPercent": 10,
            "isStopAtTarget": false,
            "maxDamageDecreaseApplyCount": 4,
            "param1": 1,
            "param2": 0,
            "shape": 67
          }
        }
      ],
      [
        {
          "baseEffectId": 5,
          "className": "EffectInstanceDice",
          "delay": 0,
          "diceNum": 20,
          "diceSide": 0,
          "dispellable": 1,
          "displayZero": false,
          "duration": 0,
          "effectElement": -1,
          "effectId": 125,
          "effectTriggerDuration": 0,
          "effectUid": 0,
          "forClientOnly": false,
          "group": 0,
          "m_flags": 8,
          "modificator": 0,
          "order": 0,
          "random": 0,
          "spellId": -1,
          "targetId": 0,
          "targetMask": "",
          "trigger": false,
          "triggers": "",
          "value": 0,
          "visibleInBuffUi": false,
          "visibleInFightLog": false,
          "visibleInTooltip": false,
          "visibleOnTerrain": true,
          "zoneDescr": {
            "cellIds": [],
            "damageDecreaseStepPercent": 10,
            "isStopAtTarget": false,
            "maxDamageDecreaseApplyCount": 4,
            "param1": 1,
            "param2": 0,
            "shape": 67
          }
        },
        {
          "baseEffectId": 6,
          "className": "EffectInstanceDice",
          "delay": 0,
          "diceNum": 20,
          "diceSide": 0,
          "dispellable": 1,
          "displayZero": false,
          "duration": 0,
          "effectElement": -1,
          "effectId": 124,
          "effectTriggerDuration": 0,
          "effectUid": 0,
          "forClientOnly": false,
          "group": 0,
          "m_flags": 8,
          "modificator": 0,
          "order": 0,
          "random": 0,
          "spellId": -1,
          "targetId": 0,
          "targetMask": "",
          "trigger": false,
          "triggers": "",
          "value": 0,
          "visibleInBuffUi": false,
          "visibleInFightLog": false,
          "visibleInTooltip": false,
          "visibleOnTerrain": true,
          "zoneDescr": {
            "cellIds": [],
            "damageDecreaseStepPercent": 10,
            "isStopAtTarget": false,
            "maxDamageDecreaseApplyCount": 4,
            "param1": 1,
            "param2": 0,
            "shape": 67
          }
        },
        {
          "baseEffectId": 22,
          "className": "EffectInstanceDice",
          "delay": 0,
          "diceNum": 20,
          "diceSide": 0,
          "dispellable": 1,
          "displayZero": false,
          "duration": 0,
          "effectElement": -1,
          "effectId": 138,
          "effectTriggerDuration": 0,
          "effectUid": 0,
          "forClientOnly": false,
          "group": 0,
          "m_flags": 8,
          "modificator": 0,
          "order": 0,
          "random": 0,
          "spellId": -1,
          "targetId": 0,
          "targetMask": "",
          "trigger": false,
          "triggers": "",
          "value": 0,
          "visibleInBuffUi": false,
          "visibleInFightLog": false,
          "visibleInTooltip": false,
          "visibleOnTerrain": true,
          "zoneDescr": {
            "cellIds": [],
            "damageDecreaseStepPercent": 10,
            "isStopAtTarget": false,
            "maxDamageDecreaseApplyCount": 4,
            "param1": 1,
            "param2": 0,
            "shape": 67
          }
        },
        {
          "baseEffectId": 11,
          "className": "EffectInstanceDice",
          "delay": 0,
          "diceNum": 1,
          "diceSide": 0,
          "dispellable": 1,
          "displayZero": false,
          "duration": 0,
          "effectElement": -1,
          "effectId": 117,
          "effectTriggerDuration": 0,
          "effectUid": 0,
          "forClientOnly": false,
          "group": 0,
          "m_flags": 8,
          "modificator": 0,
          "order": 0,
          "random": 0,
          "spellId": -1,
          "targetId": 0,
          "targetMask": "",
          "trigger": false,
          "triggers": "",
          "value": 0,
          "visibleInBuffUi": false,
          "visibleInFightLog": false,
          "visibleInTooltip": false,
          "visibleOnTerrain": true,
          "zoneDescr": {
            "cellIds": [],
            "damageDecreaseStepPercent": 10,
            "isStopAtTarget": false,
            "maxDamageDecreaseApplyCount": 4,
            "param1": 1,
            "param2": 0,
            "shape": 67
          }
        }
      ],
      [
        {
          "baseEffectId": 5,
          "className": "EffectInstanceDice",
          "delay": 0,
          "diceNum": 40,
          "diceSide": 0,
          "dispellable": 1,
          "displayZero": false,
          "duration": 0,
          "effectElement": -1,
          "effectId": 125,
          "effectTriggerDuration": 0,
          "effectUid": 0,
          "forClientOnly": false,
          "group": 0,
          "m_flags": 8,
          "modificator": 0,
          "order": 0,
          "random": 0,
          "spellId": -1,
          "targetId": 0,
          "targetMask": "",
          "trigger": false,
          "triggers": "",
          "value": 0,
          "visibleInBuffUi": false,
          "visibleInFightLog": false,
          "visibleInTooltip": false,
          "visibleOnTerrain": true,
          "zoneDescr": {
            "cellIds": [],
            "damageDecreaseStepPercent": 10,
            "isStopAtTarget": false,
            "maxDamageDecreaseApplyCount": 4,
            "param1": 1,
            "param2": 0,
            "shape": 67
          }
        },
        {
          "baseEffectId": 6,
          "className": "EffectInstanceDice",
          "delay": 0,
          "diceNum": 40,
          "diceSide": 0,
          "dispellable": 1,
          "displayZero": false,
          "duration": 0,
          "effectElement": -1,
          "effectId": 124,
          "effectTriggerDuration": 0,
          "effectUid": 0,
          "forClientOnly": false,
          "group": 0,
          "m_flags": 8,
          "modificator": 0,
          "order": 0,
          "random": 0,
          "spellId": -1,
          "targetId": 0,
          "targetMask": "",
          "trigger": false,
          "triggers": "",
          "value": 0,
          "visibleInBuffUi": false,
          "visibleInFightLog": false,
          "visibleInTooltip": false,
          "visibleOnTerrain": true,
          "zoneDescr": {
            "cellIds": [],
            "damageDecreaseStepPercent": 10,
            "isStopAtTarget": false,
            "maxDamageDecreaseApplyCount": 4,
            "param1": 1,
            "param2": 0,
            "shape": 67
          }
        },
        {
          "baseEffectId": 22,
          "className": "EffectInstanceDice",
          "delay": 0,
          "diceNum": 40,
          "diceSide": 0,
          "dispellable": 1,
          "displayZero": false,
          "duration": 0,
          "effectElement": -1,
          "effectId": 138,
          "effectTriggerDuration": 0,
          "effectUid": 0,
          "forClientOnly": false,
          "group": 0,
          "m_flags": 8,
          "modificator": 0,
          "order": 0,
          "random": 0,
          "spellId": -1,
          "targetId": 0,
          "targetMask": "",
          "trigger": false,
          "triggers": "",
          "value": 0,
          "visibleInBuffUi": false,
          "visibleInFightLog": false,
          "visibleInTooltip": false,
          "visibleOnTerrain": true,
          "zoneDescr": {
            "cellIds": [],
            "damageDecreaseStepPercent": 10,
            "isStopAtTarget": false,
            "maxDamageDecreaseApplyCount": 4,
            "param1": 1,
            "param2": 0,
            "shape": 67
          }
        },
        {
          "baseEffectId": 11,
          "className": "EffectInstanceDice",
          "delay": 0,
          "diceNum": 2,
          "diceSide": 0,
          "dispellable": 1,
          "displayZero": false,
          "duration": 0,
          "effectElement": -1,
          "effectId": 117,
          "effectTriggerDuration": 0,
          "effectUid": 0,
          "forClientOnly": false,
          "group": 0,
          "m_flags": 8,
          "modificator": 0,
          "order": 0,
          "random": 0,
          "spellId": -1,
          "targetId": 0,
          "targetMask": "",
          "trigger": false,
          "triggers": "",
          "value": 0,
          "visibleInBuffUi": false,
          "visibleInFightLog": false,
          "visibleInTooltip": false,
          "visibleOnTerrain": true,
          "zoneDescr": {
            "cellIds": [],
            "damageDecreaseStepPercent": 10,
            "isStopAtTarget": false,
            "maxDamageDecreaseApplyCount": 4,
            "param1": 1,
            "param2": 0,
            "shape": 67
          }
        },
        {
          "baseEffectId": 2,
          "className": "EffectInstanceDice",
          "delay": 0,
          "diceNum": 1,
          "diceSide": 0,
          "dispellable": 1,
          "displayZero": false,
          "duration": 0,
          "effectElement": -1,
          "effectId": 111,
          "effectTriggerDuration": 0,
          "effectUid": 0,
          "forClientOnly": false,
          "group": 0,
          "m_flags": 8,
          "modificator": 0,
          "order": 0,
          "random": 0,
          "spellId": -1,
          "targetId": 0,
          "targetMask": "",
          "trigger": false,
          "triggers": "",
          "value": 0,
          "visibleInBuffUi": false,
          "visibleInFightLog": false,
          "visibleInTooltip": false,
          "visibleOnTerrain": true,
          "zoneDescr": {
            "cellIds": [],
            "damageDecreaseStepPercent": 10,
            "isStopAtTarget": false,
            "maxDamageDecreaseApplyCount": 4,
            "param1": 1,
            "param2": 0,
            "shape": 67
          }
        }
      ]
    ],
    "slug": {
      "de": "truhen-set",
      "en": "chest set",
      "es": "set cofre",
      "fr": "panoplie coffre",
      "pt": "conjunto bau"
    },
    "typeIds": [
      16,
      10,
      1,
      11
    ],
    "updatedAt": "2025-09-23T12:09:09.355Z"
  },
  "itemSetId": 246,
  "legendaryTreasureHuntThatReward": 0,
  "level": 53,
  "m_flags": 1092,
  "m_id": 13139,
  "name": {
    "de": "Truhschuh",
    "en": "Chesty Boots",
    "es": "Cofrotas",
    "fr": "Boffes Cottre",
    "id": "98029",
    "pt": "Bofres Cota"
  },
  "needUseConfirm": false,
  "nonUsableOnAnother": false,
  "possibleEffects": [
    {
      "baseEffectId": 5,
      "className": "EffectInstanceDice",
      "delay": 0,
      "diceNum": 16,
      "diceSide": 20,
      "dispellable": 1,
      "displayZero": false,
      "duration": 0,
      "effectElement": -1,
      "effectId": 125,
      "effectTriggerDuration": 0,
      "effectUid": 0,
      "forClientOnly": false,
      "group": 0,
      "m_flags": 15,
      "modificator": 0,
      "order": 0,
      "random": 0,
      "spellId": -1,
      "targetId": 0,
      "targetMask": "",
      "trigger": false,
      "triggers": "",
      "value": 0,
      "visibleInBuffUi": true,
      "visibleInFightLog": true,
      "visibleInTooltip": true,
      "visibleOnTerrain": true,
      "zoneDescr": {
        "cellIds": [],
        "damageDecreaseStepPercent": 10,
        "isStopAtTarget": false,
        "maxDamageDecreaseApplyCount": 4,
        "param1": 1,
        "param2": 0,
        "shape": 67
      }
    },
    {
      "baseEffectId": 10,
      "className": "EffectInstanceDice",
      "delay": 0,
      "diceNum": 2,
      "diceSide": 0,
      "dispellable": 1,
      "displayZero": false,
      "duration": 0,
      "effectElement": -1,
      "effectId": 115,
      "effectTriggerDuration": 0,
      "effectUid": 0,
      "forClientOnly": false,
      "group": 0,
      "m_flags": 15,
      "modificator": 0,
      "order": 0,
      "random": 0,
      "spellId": -1,
      "targetId": 0,
      "targetMask": "",
      "trigger": false,
      "triggers": "",
      "value": 0,
      "visibleInBuffUi": true,
      "visibleInFightLog": true,
      "visibleInTooltip": true,
      "visibleOnTerrain": true,
      "zoneDescr": {
        "cellIds": [],
        "damageDecreaseStepPercent": 10,
        "isStopAtTarget": false,
        "maxDamageDecreaseApplyCount": 4,
        "param1": 1,
        "param2": 0,
        "shape": 67
      }
    },
    {
      "baseEffectId": 3,
      "className": "EffectInstanceDice",
      "delay": 0,
      "diceNum": 1,
      "diceSide": 0,
      "dispellable": 1,
      "displayZero": false,
      "duration": 0,
      "effectElement": -1,
      "effectId": 128,
      "effectTriggerDuration": 0,
      "effectUid": 0,
      "forClientOnly": false,
      "group": 0,
      "m_flags": 15,
      "modificator": 0,
      "order": 0,
      "random": 0,
      "spellId": -1,
      "targetId": 0,
      "targetMask": "",
      "trigger": false,
      "triggers": "",
      "value": 0,
      "visibleInBuffUi": true,
      "visibleInFightLog": true,
      "visibleInTooltip": true,
      "visibleOnTerrain": true,
      "zoneDescr": {
        "cellIds": [],
        "damageDecreaseStepPercent": 10,
        "isStopAtTarget": false,
        "maxDamageDecreaseApplyCount": 4,
        "param1": 1,
        "param2": 0,
        "shape": 67
      }
    },
    {
      "baseEffectId": 372,
      "className": "EffectInstanceDice",
      "delay": 0,
      "diceNum": 2,
      "diceSide": 3,
      "dispellable": 1,
      "displayZero": false,
      "duration": 0,
      "effectElement": -1,
      "effectId": 428,
      "effectTriggerDuration": 0,
      "effectUid": 0,
      "forClientOnly": false,
      "group": 0,
      "m_flags": 15,
      "modificator": 0,
      "order": 0,
      "random": 0,
      "spellId": -1,
      "targetId": 0,
      "targetMask": "",
      "trigger": false,
      "triggers": "",
      "value": 0,
      "visibleInBuffUi": true,
      "visibleInFightLog": true,
      "visibleInTooltip": true,
      "visibleOnTerrain": true,
      "zoneDescr": {
        "cellIds": [],
        "damageDecreaseStepPercent": 10,
        "isStopAtTarget": false,
        "maxDamageDecreaseApplyCount": 4,
        "param1": 1,
        "param2": 0,
        "shape": 67
      }
    },
    {
      "baseEffectId": 351,
      "className": "EffectInstanceDice",
      "delay": 0,
      "diceNum": 2,
      "diceSide": 3,
      "dispellable": 1,
      "displayZero": false,
      "duration": 0,
      "effectElement": -1,
      "effectId": 161,
      "effectTriggerDuration": 0,
      "effectUid": 0,
      "forClientOnly": false,
      "group": 0,
      "m_flags": 15,
      "modificator": 0,
      "order": 0,
      "random": 0,
      "spellId": -1,
      "targetId": 0,
      "targetMask": "",
      "trigger": false,
      "triggers": "",
      "value": 0,
      "visibleInBuffUi": true,
      "visibleInFightLog": true,
      "visibleInTooltip": true,
      "visibleOnTerrain": true,
      "zoneDescr": {
        "cellIds": [],
        "damageDecreaseStepPercent": 10,
        "isStopAtTarget": false,
        "maxDamageDecreaseApplyCount": 4,
        "param1": 1,
        "param2": 0,
        "shape": 67
      }
    },
    {
      "baseEffectId": 364,
      "className": "EffectInstanceDice",
      "delay": 0,
      "diceNum": 10,
      "diceSide": 0,
      "dispellable": 1,
      "displayZero": false,
      "duration": 0,
      "effectElement": -1,
      "effectId": 421,
      "effectTriggerDuration": 0,
      "effectUid": 0,
      "forClientOnly": false,
      "group": 0,
      "m_flags": 15,
      "modificator": 0,
      "order": 0,
      "random": 0,
      "spellId": -1,
      "targetId": 0,
      "targetMask": "",
      "trigger": false,
      "triggers": "",
      "value": 0,
      "visibleInBuffUi": true,
      "visibleInFightLog": true,
      "visibleInTooltip": true,
      "visibleOnTerrain": true,
      "zoneDescr": {
        "cellIds": [],
        "damageDecreaseStepPercent": 10,
        "isStopAtTarget": false,
        "maxDamageDecreaseApplyCount": 4,
        "param1": 1,
        "param2": 0,
        "shape": 67
      }
    },
    {
      "baseEffectId": 360,
      "className": "EffectInstanceDice",
      "delay": 0,
      "diceNum": 10,
      "diceSide": 0,
      "dispellable": 1,
      "displayZero": false,
      "duration": 0,
      "effectElement": -1,
      "effectId": 417,
      "effectTriggerDuration": 0,
      "effectUid": 0,
      "forClientOnly": false,
      "group": 0,
      "m_flags": 15,
      "modificator": 0,
      "order": 0,
      "random": 0,
      "spellId": -1,
      "targetId": 0,
      "targetMask": "",
      "trigger": false,
      "triggers": "",
      "value": 0,
      "visibleInBuffUi": true,
      "visibleInFightLog": true,
      "visibleInTooltip": true,
      "visibleOnTerrain": true,
      "zoneDescr": {
        "cellIds": [],
        "damageDecreaseStepPercent": 10,
        "isStopAtTarget": false,
        "maxDamageDecreaseApplyCount": 4,
        "param1": 1,
        "param2": 0,
        "shape": 67
      }
    }
  ],
  "price": 5300,
  "questsThatReward": [],
  "questsThatUse": [],
  "realWeight": 10,
  "recipeIds": [],
  "recipeSlots": 4,
  "recipesThatUse": [],
  "recyclingNuggets": 0,
  "resourcesBySubarea": [],
  "secretRecipe": false,
  "slug": {
    "de": "truhschuh",
    "en": "chesty boots",
    "es": "cofrotas",
    "fr": "boffes cottre",
    "pt": "bofres cota"
  },
  "startLegendaryTreasureHunt": 0,
  "targetable": false,
  "twoHanded": false,
  "type": {
    "_id": "674e524064788cc74141840e",
    "categoryId": 0,
    "className": "ItemTypeData",
    "craftXpRatio": -1,
    "createdAt": "2024-12-03T00:35:12.568Z",
    "evolutiveTypeId": 0,
    "id": 11,
    "isInEncyclopedia": true,
    "m_id": 11,
    "name": {
      "de": "Stiefel",
      "en": "Boots",
      "es": "Bota",
      "fr": "Bottes",
      "id": "29692",
      "pt": "Botas"
    },
    "rawZone": "",
    "superType": {
      "_id": "60abc3afa664687005dfd1be",
      "className": "ItemSuperTypeData",
      "createdAt": "2021-05-24T15:16:28.560Z",
      "id": 5,
      "m_id": 5,
      "name": {
        "de": "Stiefel",
        "en": "Boots",
        "es": "Botas",
        "fr": "Bottes",
        "pt": "Botas"
      },
      "positions": [
        5
      ],
      "updatedAt": "2025-09-23T12:09:10.064Z"
    },
    "superTypeId": 5,
    "updatedAt": "2025-09-23T12:09:10.308Z"
  },
  "typeId": 11,
  "updatedAt": "2025-09-23T12:09:25.438Z",
  "usable": false,
  "visibilityCriterion": ""
}